[
  {
    "archetype": "playmaker",
    "ratings": [
      {
        "metaRating": 95.29622858122168,
        "chemstyleId": 250,
        "playerRoleId": 31,
        "chemistry": 0,
        "isBestChemstyleAtChem": true
      },
      {
        "metaRating": 95.1346647388765,
        "chemstyleId": 250,
        "playerRoleId": 32,
        "chemistry": 0,
        "isBestChemstyleAtChem": true
      },
      {
        "metaRating": 94.52835970099954,
        "chemstyleId": 250,
        "playerRoleId": 35,
        "chemistry": 0,
        "isBestChemstyleAtChem": true
      },
      {
        "metaRating": 94.39162883429915,
        "chemstyleId": 250,
        "playerRoleId": 36,
        "chemistry": 0,
        "isBestChemstyleAtChem": true
      },
      {
        "metaRating": 94.26792501565124,
        "chemstyleId": 250,
        "playerRoleId": 34,
        "chemistry": 0,
        "isBestChemstyleAtChem": true
      },
      {
        "metaRating": 92.94864884709415,
        "chemstyleId": 250,
        "playerRoleId": 43,
        "chemistry": 0,
        "isBestChemstyleAtChem": true
      },
      {
        "metaRating": 92.29464728184834,
        "chemstyleId": 250,
        "playerRoleId": 33,
        "chemistry": 0,
        "isBestChemstyleAtChem": true
      },
      {
        "metaRating": 91.65798619887252,
        "chemstyleId": 250,
        "playerRoleId": 37,
        "chemistry": 0,
        "isBestChemstyleAtChem": true
      },
      {
        "metaRating": 90.62403895878573,
        "chemstyleId": 250,
        "playerRoleId": 41,
        "chemistry": 0,
        "isBestChemstyleAtChem": true
      },
      {
        "metaRating": 89.74730148891554,
        "chemstyleId": 250,
        "playerRoleId": 42,
        "chemistry": 0,
        "isBestChemstyleAtChem": true
      },
      {
        "metaRating": 80.90226135952095,
        "chemstyleId": 250,
        "playerRoleId": 44,
        "chemistry": 0,
        "isBestChemstyleAtChem": true
      },
      {
        "metaRating": 95.96742672647375,
        "chemstyleId": 266,
        "playerRoleId": 31,
        "chemistry": 1,
        "isBestChemstyleAtChem": true
      },
      {
        "metaRating": 95.91926732208822,
        "chemstyleId": 266,
        "playerRoleId": 32,
        "chemistry": 1,
        "isBestChemstyleAtChem": true
      },
      {
        "metaRating": 95.35210496533072,
        "chemstyleId": 266,
        "playerRoleId": 35,
        "chemistry": 1,
        "isBestChemstyleAtChem": true
      },
      {
        "metaRating": 95.18852163164689,
        "chemstyleId": 266,
        "playerRoleId": 36,
        "chemistry": 1,
        "isBestChemstyleAtChem": true
      },
      {
        "metaRating": 94.8206368906804,
        "chemstyleId": 266,
        "playerRoleId": 34,
        "chemistry": 1,
        "isBestChemstyleAtChem": true
      },
      {
        "metaRating": 93.70088026736178,
        "chemstyleId": 266,
        "playerRoleId": 43,
        "chemistry": 1,
        "isBestChemstyleAtChem": true
      },
      {
        "metaRating": 93.00854230991257,
        "chemstyleId": 266,
        "playerRoleId": 33,
        "chemistry": 1,
        "isBestChemstyleAtChem": true
      },
      {
        "metaRating": 92.44510488990475,
        "chemstyleId": 266,
        "playerRoleId": 37,
        "chemistry": 1,
        "isBestChemstyleAtChem": true
      },
      {
        "metaRating": 91.75927781519208,
        "chemstyleId": 266,
        "playerRoleId": 41,
        "chemistry": 1,
        "isBestChemstyleAtChem": true
      },
      {
        "metaRating": 90.99685076129512,
        "chemstyleId": 266,
        "playerRoleId": 42,
        "chemistry": 1,
        "isBestChemstyleAtChem": true
      },
      {
        "metaRating": 81.79482381912382,
        "chemstyleId": 255,
        "playerRoleId": 44,
        "chemistry": 1,
        "isBestChemstyleAtChem": true
      },
      {
        "metaRating": 96.5216775953432,
        "chemstyleId": 266,
        "playerRoleId": 32,
        "chemistry": 2,
        "isBestChemstyleAtChem": true
      },
      {
        "metaRating": 96.50701109845929,
        "chemstyleId": 266,
        "playerRoleId": 31,
        "chemistry": 2,
        "isBestChemstyleAtChem": true
      },
      {
        "metaRating": 95.96694536356718,
        "chemstyleId": 266,
        "playerRoleId": 35,
        "chemistry": 2,
        "isBestChemstyleAtChem": true
      },
      {
        "metaRating": 95.78412195651714,
        "chemstyleId": 266,
        "playerRoleId": 36,
        "chemistry": 2,
        "isBestChemstyleAtChem": true
      },
      {
        "metaRating": 95.274567509594,
        "chemstyleId": 266,
        "playerRoleId": 34,
        "chemistry": 2,
        "isBestChemstyleAtChem": true
      },
      {
        "metaRating": 94.26989549699208,
        "chemstyleId": 266,
        "playerRoleId": 43,
        "chemistry": 2,
        "isBestChemstyleAtChem": true
      },
      {
        "metaRating": 93.54264194512889,
        "chemstyleId": 266,
        "playerRoleId": 33,
        "chemistry": 2,
        "isBestChemstyleAtChem": true
      },
      {
        "metaRating": 93.04498201806422,
        "chemstyleId": 266,
        "playerRoleId": 37,
        "chemistry": 2,
        "isBestChemstyleAtChem": true
      },
      {
        "metaRating": 92.67152530892203,
        "chemstyleId": 266,
        "playerRoleId": 41,
        "chemistry": 2,
        "isBestChemstyleAtChem": true
      },
      {
        "metaRating": 91.99427296085389,
        "chemstyleId": 266,
        "playerRoleId": 42,
        "chemistry": 2,
        "isBestChemstyleAtChem": true
      },
      {
        "metaRating": 82.52038024819447,
        "chemstyleId": 255,
        "playerRoleId": 44,
        "chemistry": 2,
        "isBestChemstyleAtChem": true
      },
      {
        "metaRating": 96.97438532344394,
        "chemstyleId": 255,
        "playerRoleId": 32,
        "chemistry": 3,
        "isBestChemstyleAtChem": true
      },
      {
        "metaRating": 96.88756552581859,
        "chemstyleId": 255,
        "playerRoleId": 31,
        "chemistry": 3,
        "isBestChemstyleAtChem": true
      },
      {
        "metaRating": 96.26664547036961,
        "chemstyleId": 266,
        "playerRoleId": 35,
        "chemistry": 3,
        "isBestChemstyleAtChem": true
      },
      {
        "metaRating": 96.11492393059093,
        "chemstyleId": 266,
        "playerRoleId": 36,
        "chemistry": 3,
        "isBestChemstyleAtChem": true
      },
      {
        "metaRating": 95.52232520121701,
        "chemstyleId": 266,
        "playerRoleId": 34,
        "chemistry": 3,
        "isBestChemstyleAtChem": true
      },
      {
        "metaRating": 94.84769612152252,
        "chemstyleId": 255,
        "playerRoleId": 43,
        "chemistry": 3,
        "isBestChemstyleAtChem": true
      },
      {
        "metaRating": 93.81202970023092,
        "chemstyleId": 266,
        "playerRoleId": 33,
        "chemistry": 3,
        "isBestChemstyleAtChem": true
      },
      {
        "metaRating": 93.40529584679197,
        "chemstyleId": 266,
        "playerRoleId": 37,
        "chemistry": 3,
        "isBestChemstyleAtChem": true
      },
      {
        "metaRating": 93.24703334410121,
        "chemstyleId": 266,
        "playerRoleId": 41,
        "chemistry": 3,
        "isBestChemstyleAtChem": true
      },
      {
        "metaRating": 92.60677294386315,
        "chemstyleId": 266,
        "playerRoleId": 42,
        "chemistry": 3,
        "isBestChemstyleAtChem": true
      },
      {
        "metaRating": 83.90061955083245,
        "chemstyleId": 255,
        "playerRoleId": 44,
        "chemistry": 3,
        "isBestChemstyleAtChem": true
      }
    ]
  },
  {
    "archetype": "half_winger",
    "ratings": [
      {
        "metaRating": 95.29622858122168,
        "chemstyleId": 250,
        "playerRoleId": 31,
        "chemistry": 0,
        "isBestChemstyleAtChem": true
      },
      {
        "metaRating": 95.1346647388765,
        "chemstyleId": 250,
        "playerRoleId": 32,
        "chemistry": 0,
        "isBestChemstyleAtChem": true
      },
      {
        "metaRating": 94.52835970099954,
        "chemstyleId": 250,
        "playerRoleId": 35,
        "chemistry": 0,
        "isBestChemstyleAtChem": true
      },
      {
        "metaRating": 94.39162883429915,
        "chemstyleId": 250,
        "playerRoleId": 36,
        "chemistry": 0,
        "isBestChemstyleAtChem": true
      },
      {
        "metaRating": 94.26792501565124,
        "chemstyleId": 250,
        "playerRoleId": 34,
        "chemistry": 0,
        "isBestChemstyleAtChem": true
      },
      {
        "metaRating": 92.94864884709415,
        "chemstyleId": 250,
        "playerRoleId": 43,
        "chemistry": 0,
        "isBestChemstyleAtChem": true
      },
      {
        "metaRating": 92.29464728184834,
        "chemstyleId": 250,
        "playerRoleId": 33,
        "chemistry": 0,
        "isBestChemstyleAtChem": true
      },
      {
        "metaRating": 91.65798619887252,
        "chemstyleId": 250,
        "playerRoleId": 37,
        "chemistry": 0,
        "isBestChemstyleAtChem": true
      },
      {
        "metaRating": 90.62403895878573,
        "chemstyleId": 250,
        "playerRoleId": 41,
        "chemistry": 0,
        "isBestChemstyleAtChem": true
      },
      {
        "metaRating": 89.74730148891554,
        "chemstyleId": 250,
        "playerRoleId": 42,
        "chemistry": 0,
        "isBestChemstyleAtChem": true
      },
      {
        "metaRating": 80.90226135952095,
        "chemstyleId": 250,
        "playerRoleId": 44,
        "chemistry": 0,
        "isBestChemstyleAtChem": true
      },
      {
        "metaRating": 95.96742672647375,
        "chemstyleId": 266,
        "playerRoleId": 31,
        "chemistry": 1,
        "isBestChemstyleAtChem": true
      },
      {
        "metaRating": 95.91926732208822,
        "chemstyleId": 266,
        "playerRoleId": 32,
        "chemistry": 1,
        "isBestChemstyleAtChem": true
      },
      {
        "metaRating": 95.35210496533072,
        "chemstyleId": 266,
        "playerRoleId": 35,
        "chemistry": 1,
        "isBestChemstyleAtChem": true
      },
      {
        "metaRating": 95.18852163164689,
        "chemstyleId": 266,
        "playerRoleId": 36,
        "chemistry": 1,
        "isBestChemstyleAtChem": true
      },
      {
        "metaRating": 94.8206368906804,
        "chemstyleId": 266,
        "playerRoleId": 34,
        "chemistry": 1,
        "isBestChemstyleAtChem": true
      },
      {
        "metaRating": 93.70088026736178,
        "chemstyleId": 266,
        "playerRoleId": 43,
        "chemistry": 1,
        "isBestChemstyleAtChem": true
      },
      {
        "metaRating": 93.00854230991257,
        "chemstyleId": 266,
        "playerRoleId": 33,
        "chemistry": 1,
        "isBestChemstyleAtChem": true
      },
      {
        "metaRating": 92.44510488990475,
        "chemstyleId": 266,
        "playerRoleId": 37,
        "chemistry": 1,
        "isBestChemstyleAtChem": true
      },
      {
        "metaRating": 91.75927781519208,
        "chemstyleId": 266,
        "playerRoleId": 41,
        "chemistry": 1,
        "isBestChemstyleAtChem": true
      },
      {
        "metaRating": 90.99685076129512,
        "chemstyleId": 266,
        "playerRoleId": 42,
        "chemistry": 1,
        "isBestChemstyleAtChem": true
      },
      {
        "metaRating": 81.79482381912382,
        "chemstyleId": 255,
        "playerRoleId": 44,
        "chemistry": 1,
        "isBestChemstyleAtChem": true
      },
      {
        "metaRating": 96.5216775953432,
        "chemstyleId": 266,
        "playerRoleId": 32,
        "chemistry": 2,
        "isBestChemstyleAtChem": true
      },
      {
        "metaRating": 96.50701109845929,
        "chemstyleId": 266,
        "playerRoleId": 31,
        "chemistry": 2,
        "isBestChemstyleAtChem": true
      },
      {
        "metaRating": 95.96694536356718,
        "chemstyleId": 266,
        "playerRoleId": 35,
        "chemistry": 2,
        "isBestChemstyleAtChem": true
      },
      {
        "metaRating": 95.78412195651714,
        "chemstyleId": 266,
        "playerRoleId": 36,
        "chemistry": 2,
        "isBestChemstyleAtChem": true
      },
      {
        "metaRating": 95.274567509594,
        "chemstyleId": 266,
        "playerRoleId": 34,
        "chemistry": 2,
        "isBestChemstyleAtChem": true
      },
      {
        "metaRating": 94.26989549699208,
        "chemstyleId": 266,
        "playerRoleId": 43,
        "chemistry": 2,
        "isBestChemstyleAtChem": true
      },
      {
        "metaRating": 93.54264194512889,
        "chemstyleId": 266,
        "playerRoleId": 33,
        "chemistry": 2,
        "isBestChemstyleAtChem": true
      },
      {
        "metaRating": 93.04498201806422,
        "chemstyleId": 266,
        "playerRoleId": 37,
        "chemistry": 2,
        "isBestChemstyleAtChem": true
      },
      {
        "metaRating": 92.67152530892203,
        "chemstyleId": 266,
        "playerRoleId": 41,
        "chemistry": 2,
        "isBestChemstyleAtChem": true
      },
      {
        "metaRating": 91.99427296085389,
        "chemstyleId": 266,
        "playerRoleId": 42,
        "chemistry": 2,
        "isBestChemstyleAtChem": true
      },
      {
        "metaRating": 82.52038024819447,
        "chemstyleId": 255,
        "playerRoleId": 44,
        "chemistry": 2,
        "isBestChemstyleAtChem": true
      },
      {
        "metaRating": 96.97438532344394,
        "chemstyleId": 255,
        "playerRoleId": 32,
        "chemistry": 3,
        "isBestChemstyleAtChem": true
      },
      {
        "metaRating": 96.88756552581859,
        "chemstyleId": 255,
        "playerRoleId": 31,
        "chemistry": 3,
        "isBestChemstyleAtChem": true
      },
      {
        "metaRating": 96.26664547036961,
        "chemstyleId": 266,
        "playerRoleId": 35,
        "chemistry": 3,
        "isBestChemstyleAtChem": true
      },
      {
        "metaRating": 96.11492393059093,
        "chemstyleId": 266,
        "playerRoleId": 36,
        "chemistry": 3,
        "isBestChemstyleAtChem": true
      },
      {
        "metaRating": 95.52232520121701,
        "chemstyleId": 266,
        "playerRoleId": 34,
        "chemistry": 3,
        "isBestChemstyleAtChem": true
      },
      {
        "metaRating": 94.84769612152252,
        "chemstyleId": 255,
        "playerRoleId": 43,
        "chemistry": 3,
        "isBestChemstyleAtChem": true
      },
      {
        "metaRating": 93.81202970023092,
        "chemstyleId": 266,
        "playerRoleId": 33,
        "chemistry": 3,
        "isBestChemstyleAtChem": true
      },
      {
        "metaRating": 93.40529584679197,
        "chemstyleId": 266,
        "playerRoleId": 37,
        "chemistry": 3,
        "isBestChemstyleAtChem": true
      },
      {
        "metaRating": 93.24703334410121,
        "chemstyleId": 266,
        "playerRoleId": 41,
        "chemistry": 3,
        "isBestChemstyleAtChem": true
      },
      {
        "metaRating": 92.60677294386315,
        "chemstyleId": 266,
        "playerRoleId": 42,
        "chemistry": 3,
        "isBestChemstyleAtChem": true
      },
      {
        "metaRating": 83.90061955083245,
        "chemstyleId": 255,
        "playerRoleId": 44,
        "chemistry": 3,
        "isBestChemstyleAtChem": true
      }
    ]
  },
  {
    "archetype": "classic_ten",
    "ratings": [
      {
        "metaRating": 95.29622858122168,
        "chemstyleId": 250,
        "playerRoleId": 31,
        "chemistry": 0,
        "isBestChemstyleAtChem": true
      },
      {
        "metaRating": 95.1346647388765,
        "chemstyleId": 250,
        "playerRoleId": 32,
        "chemistry": 0,
        "isBestChemstyleAtChem": true
      },
      {
        "metaRating": 94.52835970099954,
        "chemstyleId": 250,
        "playerRoleId": 35,
        "chemistry": 0,
        "isBestChemstyleAtChem": true
      },
      {
        "metaRating": 94.39162883429915,
        "chemstyleId": 250,
        "playerRoleId": 36,
        "chemistry": 0,
        "isBestChemstyleAtChem": true
      },
      {
        "metaRating": 94.26792501565124,
        "chemstyleId": 250,
        "playerRoleId": 34,
        "chemistry": 0,
        "isBestChemstyleAtChem": true
      },
      {
        "metaRating": 92.94864884709415,
        "chemstyleId": 250,
        "playerRoleId": 43,
        "chemistry": 0,
        "isBestChemstyleAtChem": true
      },
      {
        "metaRating": 92.29464728184834,
        "chemstyleId": 250,
        "playerRoleId": 33,
        "chemistry": 0,
        "isBestChemstyleAtChem": true
      },
      {
        "metaRating": 91.65798619887252,
        "chemstyleId": 250,
        "playerRoleId": 37,
        "chemistry": 0,
        "isBestChemstyleAtChem": true
      },
      {
        "metaRating": 90.62403895878573,
        "chemstyleId": 250,
        "playerRoleId": 41,
        "chemistry": 0,
        "isBestChemstyleAtChem": true
      },
      {
        "metaRating": 89.74730148891554,
        "chemstyleId": 250,
        "playerRoleId": 42,
        "chemistry": 0,
        "isBestChemstyleAtChem": true
      },
      {
        "metaRating": 80.90226135952095,
        "chemstyleId": 250,
        "playerRoleId": 44,
        "chemistry": 0,
        "isBestChemstyleAtChem": true
      },
      {
        "metaRating": 95.96742672647375,
        "chemstyleId": 266,
        "playerRoleId": 31,
        "chemistry": 1,
        "isBestChemstyleAtChem": true
      },
      {
        "metaRating": 95.91926732208822,
        "chemstyleId": 266,
        "playerRoleId": 32,
        "chemistry": 1,
        "isBestChemstyleAtChem": true
      },
      {
        "metaRating": 95.35210496533072,
        "chemstyleId": 266,
        "playerRoleId": 35,
        "chemistry": 1,
        "isBestChemstyleAtChem": true
      },
      {
        "metaRating": 95.18852163164689,
        "chemstyleId": 266,
        "playerRoleId": 36,
        "chemistry": 1,
        "isBestChemstyleAtChem": true
      },
      {
        "metaRating": 94.8206368906804,
        "chemstyleId": 266,
        "playerRoleId": 34,
        "chemistry": 1,
        "isBestChemstyleAtChem": true
      },
      {
        "metaRating": 93.70088026736178,
        "chemstyleId": 266,
        "playerRoleId": 43,
        "chemistry": 1,
        "isBestChemstyleAtChem": true
      },
      {
        "metaRating": 93.00854230991257,
        "chemstyleId": 266,
        "playerRoleId": 33,
        "chemistry": 1,
        "isBestChemstyleAtChem": true
      },
      {
        "metaRating": 92.44510488990475,
        "chemstyleId": 266,
        "playerRoleId": 37,
        "chemistry": 1,
        "isBestChemstyleAtChem": true
      },
      {
        "metaRating": 91.75927781519208,
        "chemstyleId": 266,
        "playerRoleId": 41,
        "chemistry": 1,
        "isBestChemstyleAtChem": true
      },
      {
        "metaRating": 90.99685076129512,
        "chemstyleId": 266,
        "playerRoleId": 42,
        "chemistry": 1,
        "isBestChemstyleAtChem": true
      },
      {
        "metaRating": 81.79482381912382,
        "chemstyleId": 255,
        "playerRoleId": 44,
        "chemistry": 1,
        "isBestChemstyleAtChem": true
      },
      {
        "metaRating": 96.5216775953432,
        "chemstyleId": 266,
        "playerRoleId": 32,
        "chemistry": 2,
        "isBestChemstyleAtChem": true
      },
      {
        "metaRating": 96.50701109845929,
        "chemstyleId": 266,
        "playerRoleId": 31,
        "chemistry": 2,
        "isBestChemstyleAtChem": true
      },
      {
        "metaRating": 95.96694536356718,
        "chemstyleId": 266,
        "playerRoleId": 35,
        "chemistry": 2,
        "isBestChemstyleAtChem": true
      },
      {
        "metaRating": 95.78412195651714,
        "chemstyleId": 266,
        "playerRoleId": 36,
        "chemistry": 2,
        "isBestChemstyleAtChem": true
      },
      {
        "metaRating": 95.274567509594,
        "chemstyleId": 266,
        "playerRoleId": 34,
        "chemistry": 2,
        "isBestChemstyleAtChem": true
      },
      {
        "metaRating": 94.26989549699208,
        "chemstyleId": 266,
        "playerRoleId": 43,
        "chemistry": 2,
        "isBestChemstyleAtChem": true
      },
      {
        "metaRating": 93.54264194512889,
        "chemstyleId": 266,
        "playerRoleId": 33,
        "chemistry": 2,
        "isBestChemstyleAtChem": true
      },
      {
        "metaRating": 93.04498201806422,
        "chemstyleId": 266,
        "playerRoleId": 37,
        "chemistry": 2,
        "isBestChemstyleAtChem": true
      },
      {
        "metaRating": 92.67152530892203,
        "chemstyleId": 266,
        "playerRoleId": 41,
        "chemistry": 2,
        "isBestChemstyleAtChem": true
      },
      {
        "metaRating": 91.99427296085389,
        "chemstyleId": 266,
        "playerRoleId": 42,
        "chemistry": 2,
        "isBestChemstyleAtChem": true
      },
      {
        "metaRating": 82.52038024819447,
        "chemstyleId": 255,
        "playerRoleId": 44,
        "chemistry": 2,
        "isBestChemstyleAtChem": true
      },
      {
        "metaRating": 96.97438532344394,
        "chemstyleId": 255,
        "playerRoleId": 32,
        "chemistry": 3,
        "isBestChemstyleAtChem": true
      },
      {
        "metaRating": 96.88756552581859,
        "chemstyleId": 255,
        "playerRoleId": 31,
        "chemistry": 3,
        "isBestChemstyleAtChem": true
      },
      {
        "metaRating": 96.26664547036961,
        "chemstyleId": 266,
        "playerRoleId": 35,
        "chemistry": 3,
        "isBestChemstyleAtChem": true
      },
      {
        "metaRating": 96.11492393059093,
        "chemstyleId": 266,
        "playerRoleId": 36,
        "chemistry": 3,
        "isBestChemstyleAtChem": true
      },
      {
        "metaRating": 95.52232520121701,
        "chemstyleId": 266,
        "playerRoleId": 34,
        "chemistry": 3,
        "isBestChemstyleAtChem": true
      },
      {
        "metaRating": 94.84769612152252,
        "chemstyleId": 255,
        "playerRoleId": 43,
        "chemistry": 3,
        "isBestChemstyleAtChem": true
      },
      {
        "metaRating": 93.81202970023092,
        "chemstyleId": 266,
        "playerRoleId": 33,
        "chemistry": 3,
        "isBestChemstyleAtChem": true
      },
      {
        "metaRating": 93.40529584679197,
        "chemstyleId": 266,
        "playerRoleId": 37,
        "chemistry": 3,
        "isBestChemstyleAtChem": true
      },
      {
        "metaRating": 93.24703334410121,
        "chemstyleId": 266,
        "playerRoleId": 41,
        "chemistry": 3,
        "isBestChemstyleAtChem": true
      },
      {
        "metaRating": 92.60677294386315,
        "chemstyleId": 266,
        "playerRoleId": 42,
        "chemistry": 3,
        "isBestChemstyleAtChem": true
      },
      {
        "metaRating": 83.90061955083245,
        "chemstyleId": 255,
        "playerRoleId": 44,
        "chemistry": 3,
        "isBestChemstyleAtChem": true
      }
    ]
  },
  {
    "archetype": "shadow_striker",
    "ratings": [
      {
        "metaRating": 95.29622858122168,
        "chemstyleId": 250,
        "playerRoleId": 31,
        "chemistry": 0,
        "isBestChemstyleAtChem": true
      },
      {
        "metaRating": 95.1346647388765,
        "chemstyleId": 250,
        "playerRoleId": 32,
        "chemistry": 0,
        "isBestChemstyleAtChem": true
      },
      {
        "metaRating": 94.52835970099954,
        "chemstyleId": 250,
        "playerRoleId": 35,
        "chemistry": 0,
        "isBestChemstyleAtChem": true
      },
      {
        "metaRating": 94.39162883429915,
        "chemstyleId": 250,
        "playerRoleId": 36,
        "chemistry": 0,
        "isBestChemstyleAtChem": true
      },
      {
        "metaRating": 94.26792501565124,
        "chemstyleId": 250,
        "playerRoleId": 34,
        "chemistry": 0,
        "isBestChemstyleAtChem": true
      },
      {
        "metaRating": 92.94864884709415,
        "chemstyleId": 250,
        "playerRoleId": 43,
        "chemistry": 0,
        "isBestChemstyleAtChem": true
      },
      {
        "metaRating": 92.29464728184834,
        "chemstyleId": 250,
        "playerRoleId": 33,
        "chemistry": 0,
        "isBestChemstyleAtChem": true
      },
      {
        "metaRating": 91.65798619887252,
        "chemstyleId": 250,
        "playerRoleId": 37,
        "chemistry": 0,
        "isBestChemstyleAtChem": true
      },
      {
        "metaRating": 90.62403895878573,
        "chemstyleId": 250,
        "playerRoleId": 41,
        "chemistry": 0,
        "isBestChemstyleAtChem": true
      },
      {
        "metaRating": 89.74730148891554,
        "chemstyleId": 250,
        "playerRoleId": 42,
        "chemistry": 0,
        "isBestChemstyleAtChem": true
      },
      {
        "metaRating": 80.90226135952095,
        "chemstyleId": 250,
        "playerRoleId": 44,
        "chemistry": 0,
        "isBestChemstyleAtChem": true
      },
      {
        "metaRating": 95.96742672647375,
        "chemstyleId": 266,
        "playerRoleId": 31,
        "chemistry": 1,
        "isBestChemstyleAtChem": true
      },
      {
        "metaRating": 95.91926732208822,
        "chemstyleId": 266,
        "playerRoleId": 32,
        "chemistry": 1,
        "isBestChemstyleAtChem": true
      },
      {
        "metaRating": 95.35210496533072,
        "chemstyleId": 266,
        "playerRoleId": 35,
        "chemistry": 1,
        "isBestChemstyleAtChem": true
      },
      {
        "metaRating": 95.18852163164689,
        "chemstyleId": 266,
        "playerRoleId": 36,
        "chemistry": 1,
        "isBestChemstyleAtChem": true
      },
      {
        "metaRating": 94.8206368906804,
        "chemstyleId": 266,
        "playerRoleId": 34,
        "chemistry": 1,
        "isBestChemstyleAtChem": true
      },
      {
        "metaRating": 93.70088026736178,
        "chemstyleId": 266,
        "playerRoleId": 43,
        "chemistry": 1,
        "isBestChemstyleAtChem": true
      },
      {
        "metaRating": 93.00854230991257,
        "chemstyleId": 266,
        "playerRoleId": 33,
        "chemistry": 1,
        "isBestChemstyleAtChem": true
      },
      {
        "metaRating": 92.44510488990475,
        "chemstyleId": 266,
        "playerRoleId": 37,
        "chemistry": 1,
        "isBestChemstyleAtChem": true
      },
      {
        "metaRating": 91.75927781519208,
        "chemstyleId": 266,
        "playerRoleId": 41,
        "chemistry": 1,
        "isBestChemstyleAtChem": true
      },
      {
        "metaRating": 90.99685076129512,
        "chemstyleId": 266,
        "playerRoleId": 42,
        "chemistry": 1,
        "isBestChemstyleAtChem": true
      },
      {
        "metaRating": 81.79482381912382,
        "chemstyleId": 255,
        "playerRoleId": 44,
        "chemistry": 1,
        "isBestChemstyleAtChem": true
      },
      {
        "metaRating": 96.5216775953432,
        "chemstyleId": 266,
        "playerRoleId": 32,
        "chemistry": 2,
        "isBestChemstyleAtChem": true
      },
      {
        "metaRating": 96.50701109845929,
        "chemstyleId": 266,
        "playerRoleId": 31,
        "chemistry": 2,
        "isBestChemstyleAtChem": true
      },
      {
        "metaRating": 95.96694536356718,
        "chemstyleId": 266,
        "playerRoleId": 35,
        "chemistry": 2,
        "isBestChemstyleAtChem": true
      },
      {
        "metaRating": 95.78412195651714,
        "chemstyleId": 266,
        "playerRoleId": 36,
        "chemistry": 2,
        "isBestChemstyleAtChem": true
      },
      {
        "metaRating": 95.274567509594,
        "chemstyleId": 266,
        "playerRoleId": 34,
        "chemistry": 2,
        "isBestChemstyleAtChem": true
      },
      {
        "metaRating": 94.26989549699208,
        "chemstyleId": 266,
        "playerRoleId": 43,
        "chemistry": 2,
        "isBestChemstyleAtChem": true
      },
      {
        "metaRating": 93.54264194512889,
        "chemstyleId": 266,
        "playerRoleId": 33,
        "chemistry": 2,
        "isBestChemstyleAtChem": true
      },
      {
        "metaRating": 93.04498201806422,
        "chemstyleId": 266,
        "playerRoleId": 37,
        "chemistry": 2,
        "isBestChemstyleAtChem": true
      },
      {
        "metaRating": 92.67152530892203,
        "chemstyleId": 266,
        "playerRoleId": 41,
        "chemistry": 2,
        "isBestChemstyleAtChem": true
      },
      {
        "metaRating": 91.99427296085389,
        "chemstyleId": 266,
        "playerRoleId": 42,
        "chemistry": 2,
        "isBestChemstyleAtChem": true
      },
      {
        "metaRating": 82.52038024819447,
        "chemstyleId": 255,
        "playerRoleId": 44,
        "chemistry": 2,
        "isBestChemstyleAtChem": true
      },
      {
        "metaRating": 96.97438532344394,
        "chemstyleId": 255,
        "playerRoleId": 32,
        "chemistry": 3,
        "isBestChemstyleAtChem": true
      },
      {
        "metaRating": 96.88756552581859,
        "chemstyleId": 255,
        "playerRoleId": 31,
        "chemistry": 3,
        "isBestChemstyleAtChem": true
      },
      {
        "metaRating": 96.26664547036961,
        "chemstyleId": 266,
        "playerRoleId": 35,
        "chemistry": 3,
        "isBestChemstyleAtChem": true
      },
      {
        "metaRating": 96.11492393059093,
        "chemstyleId": 266,
        "playerRoleId": 36,
        "chemistry": 3,
        "isBestChemstyleAtChem": true
      },
      {
        "metaRating": 95.52232520121701,
        "chemstyleId": 266,
        "playerRoleId": 34,
        "chemistry": 3,
        "isBestChemstyleAtChem": true
      },
      {
        "metaRating": 94.84769612152252,
        "chemstyleId": 255,
        "playerRoleId": 43,
        "chemistry": 3,
        "isBestChemstyleAtChem": true
      },
      {
        "metaRating": 93.81202970023092,
        "chemstyleId": 266,
        "playerRoleId": 33,
        "chemistry": 3,
        "isBestChemstyleAtChem": true
      },
      {
        "metaRating": 93.40529584679197,
        "chemstyleId": 266,
        "playerRoleId": 37,
        "chemistry": 3,
        "isBestChemstyleAtChem": true
      },
      {
        "metaRating": 93.24703334410121,
        "chemstyleId": 266,
        "playerRoleId": 41,
        "chemistry": 3,
        "isBestChemstyleAtChem": true
      },
      {
        "metaRating": 92.60677294386315,
        "chemstyleId": 266,
        "playerRoleId": 42,
        "chemistry": 3,
        "isBestChemstyleAtChem": true
      },
      {
        "metaRating": 83.90061955083245,
        "chemstyleId": 255,
        "playerRoleId": 44,
        "chemistry": 3,
        "isBestChemstyleAtChem": true
      }
    ]
  },
  {
    "archetype": "inside_forward",
    "ratings": [
      {
        "metaRating": 95.29622858122168,
        "chemstyleId": 250,
        "playerRoleId": 31,
        "chemistry": 0,
        "isBestChemstyleAtChem": true
      },
      {
        "metaRating": 95.1346647388765,
        "chemstyleId": 250,
        "playerRoleId": 32,
        "chemistry": 0,
        "isBestChemstyleAtChem": true
      },
      {
        "metaRating": 94.52835970099954,
        "chemstyleId": 250,
        "playerRoleId": 35,
        "chemistry": 0,
        "isBestChemstyleAtChem": true
      },
      {
        "metaRating": 94.39162883429915,
        "chemstyleId": 250,
        "playerRoleId": 36,
        "chemistry": 0,
        "isBestChemstyleAtChem": true
      },
      {
        "metaRating": 94.26792501565124,
        "chemstyleId": 250,
        "playerRoleId": 34,
        "chemistry": 0,
        "isBestChemstyleAtChem": true
      },
      {
        "metaRating": 92.94864884709415,
        "chemstyleId": 250,
        "playerRoleId": 43,
        "chemistry": 0,
        "isBestChemstyleAtChem": true
      },
      {
        "metaRating": 92.29464728184834,
        "chemstyleId": 250,
        "playerRoleId": 33,
        "chemistry": 0,
        "isBestChemstyleAtChem": true
      },
      {
        "metaRating": 91.65798619887252,
        "chemstyleId": 250,
        "playerRoleId": 37,
        "chemistry": 0,
        "isBestChemstyleAtChem": true
      },
      {
        "metaRating": 90.62403895878573,
        "chemstyleId": 250,
        "playerRoleId": 41,
        "chemistry": 0,
        "isBestChemstyleAtChem": true
      },
      {
        "metaRating": 89.74730148891554,
        "chemstyleId": 250,
        "playerRoleId": 42,
        "chemistry": 0,
        "isBestChemstyleAtChem": true
      },
      {
        "metaRating": 80.90226135952095,
        "chemstyleId": 250,
        "playerRoleId": 44,
        "chemistry": 0,
        "isBestChemstyleAtChem": true
      },
      {
        "metaRating": 95.96742672647375,
        "chemstyleId": 266,
        "playerRoleId": 31,
        "chemistry": 1,
        "isBestChemstyleAtChem": true
      },
      {
        "metaRating": 95.91926732208822,
        "chemstyleId": 266,
        "playerRoleId": 32,
        "chemistry": 1,
        "isBestChemstyleAtChem": true
      },
      {
        "metaRating": 95.35210496533072,
        "chemstyleId": 266,
        "playerRoleId": 35,
        "chemistry": 1,
        "isBestChemstyleAtChem": true
      },
      {
        "metaRating": 95.18852163164689,
        "chemstyleId": 266,
        "playerRoleId": 36,
        "chemistry": 1,
        "isBestChemstyleAtChem": true
      },
      {
        "metaRating": 94.8206368906804,
        "chemstyleId": 266,
        "playerRoleId": 34,
        "chemistry": 1,
        "isBestChemstyleAtChem": true
      },
      {
        "metaRating": 93.70088026736178,
        "chemstyleId": 266,
        "playerRoleId": 43,
        "chemistry": 1,
        "isBestChemstyleAtChem": true
      },
      {
        "metaRating": 93.00854230991257,
        "chemstyleId": 266,
        "playerRoleId": 33,
        "chemistry": 1,
        "isBestChemstyleAtChem": true
      },
      {
        "metaRating": 92.44510488990475,
        "chemstyleId": 266,
        "playerRoleId": 37,
        "chemistry": 1,
        "isBestChemstyleAtChem": true
      },
      {
        "metaRating": 91.75927781519208,
        "chemstyleId": 266,
        "playerRoleId": 41,
        "chemistry": 1,
        "isBestChemstyleAtChem": true
      },
      {
        "metaRating": 90.99685076129512,
        "chemstyleId": 266,
        "playerRoleId": 42,
        "chemistry": 1,
        "isBestChemstyleAtChem": true
      },
      {
        "metaRating": 81.79482381912382,
        "chemstyleId": 255,
        "playerRoleId": 44,
        "chemistry": 1,
        "isBestChemstyleAtChem": true
      },
      {
        "metaRating": 96.5216775953432,
        "chemstyleId": 266,
        "playerRoleId": 32,
        "chemistry": 2,
        "isBestChemstyleAtChem": true
      },
      {
        "metaRating": 96.50701109845929,
        "chemstyleId": 266,
        "playerRoleId": 31,
        "chemistry": 2,
        "isBestChemstyleAtChem": true
      },
      {
        "metaRating": 95.96694536356718,
        "chemstyleId": 266,
        "playerRoleId": 35,
        "chemistry": 2,
        "isBestChemstyleAtChem": true
      },
      {
        "metaRating": 95.78412195651714,
        "chemstyleId": 266,
        "playerRoleId": 36,
        "chemistry": 2,
        "isBestChemstyleAtChem": true
      },
      {
        "metaRating": 95.274567509594,
        "chemstyleId": 266,
        "playerRoleId": 34,
        "chemistry": 2,
        "isBestChemstyleAtChem": true
      },
      {
        "metaRating": 94.26989549699208,
        "chemstyleId": 266,
        "playerRoleId": 43,
        "chemistry": 2,
        "isBestChemstyleAtChem": true
      },
      {
        "metaRating": 93.54264194512889,
        "chemstyleId": 266,
        "playerRoleId": 33,
        "chemistry": 2,
        "isBestChemstyleAtChem": true
      },
      {
        "metaRating": 93.04498201806422,
        "chemstyleId": 266,
        "playerRoleId": 37,
        "chemistry": 2,
        "isBestChemstyleAtChem": true
      },
      {
        "metaRating": 92.67152530892203,
        "chemstyleId": 266,
        "playerRoleId": 41,
        "chemistry": 2,
        "isBestChemstyleAtChem": true
      },
      {
        "metaRating": 91.99427296085389,
        "chemstyleId": 266,
        "playerRoleId": 42,
        "chemistry": 2,
        "isBestChemstyleAtChem": true
      },
      {
        "metaRating": 82.52038024819447,
        "chemstyleId": 255,
        "playerRoleId": 44,
        "chemistry": 2,
        "isBestChemstyleAtChem": true
      },
      {
        "metaRating": 96.97438532344394,
        "chemstyleId": 255,
        "playerRoleId": 32,
        "chemistry": 3,
        "isBestChemstyleAtChem": true
      },
      {
        "metaRating": 96.88756552581859,
        "chemstyleId": 255,
        "playerRoleId": 31,
        "chemistry": 3,
        "isBestChemstyleAtChem": true
      },
      {
        "metaRating": 96.26664547036961,
        "chemstyleId": 266,
        "playerRoleId": 35,
        "chemistry": 3,
        "isBestChemstyleAtChem": true
      },
      {
        "metaRating": 96.11492393059093,
        "chemstyleId": 266,
        "playerRoleId": 36,
        "chemistry": 3,
        "isBestChemstyleAtChem": true
      },
      {
        "metaRating": 95.52232520121701,
        "chemstyleId": 266,
        "playerRoleId": 34,
        "chemistry": 3,
        "isBestChemstyleAtChem": true
      },
      {
        "metaRating": 94.84769612152252,
        "chemstyleId": 255,
        "playerRoleId": 43,
        "chemistry": 3,
        "isBestChemstyleAtChem": true
      },
      {
        "metaRating": 93.81202970023092,
        "chemstyleId": 266,
        "playerRoleId": 33,
        "chemistry": 3,
        "isBestChemstyleAtChem": true
      },
      {
        "metaRating": 93.40529584679197,
        "chemstyleId": 266,
        "playerRoleId": 37,
        "chemistry": 3,
        "isBestChemstyleAtChem": true
      },
      {
        "metaRating": 93.24703334410121,
        "chemstyleId": 266,
        "playerRoleId": 41,
        "chemistry": 3,
        "isBestChemstyleAtChem": true
      },
      {
        "metaRating": 92.60677294386315,
        "chemstyleId": 266,
        "playerRoleId": 42,
        "chemistry": 3,
        "isBestChemstyleAtChem": true
      },
      {
        "metaRating": 83.90061955083245,
        "chemstyleId": 255,
        "playerRoleId": 44,
        "chemistry": 3,
        "isBestChemstyleAtChem": true
      }
    ]
  },
  {
    "archetype": "winger",
    "ratings": [
      {
        "metaRating": 95.29622858122168,
        "chemstyleId": 250,
        "playerRoleId": 31,
        "chemistry": 0,
        "isBestChemstyleAtChem": true
      },
      {
        "metaRating": 95.1346647388765,
        "chemstyleId": 250,
        "playerRoleId": 32,
        "chemistry": 0,
        "isBestChemstyleAtChem": true
      },
      {
        "metaRating": 94.52835970099954,
        "chemstyleId": 250,
        "playerRoleId": 35,
        "chemistry": 0,
        "isBestChemstyleAtChem": true
      },
      {
        "metaRating": 94.39162883429915,
        "chemstyleId": 250,
        "playerRoleId": 36,
        "chemistry": 0,
        "isBestChemstyleAtChem": true
      },
      {
        "metaRating": 94.26792501565124,
        "chemstyleId": 250,
        "playerRoleId": 34,
        "chemistry": 0,
        "isBestChemstyleAtChem": true
      },
      {
        "metaRating": 92.94864884709415,
        "chemstyleId": 250,
        "playerRoleId": 43,
        "chemistry": 0,
        "isBestChemstyleAtChem": true
      },
      {
        "metaRating": 92.29464728184834,
        "chemstyleId": 250,
        "playerRoleId": 33,
        "chemistry": 0,
        "isBestChemstyleAtChem": true
      },
      {
        "metaRating": 91.65798619887252,
        "chemstyleId": 250,
        "playerRoleId": 37,
        "chemistry": 0,
        "isBestChemstyleAtChem": true
      },
      {
        "metaRating": 90.62403895878573,
        "chemstyleId": 250,
        "playerRoleId": 41,
        "chemistry": 0,
        "isBestChemstyleAtChem": true
      },
      {
        "metaRating": 89.74730148891554,
        "chemstyleId": 250,
        "playerRoleId": 42,
        "chemistry": 0,
        "isBestChemstyleAtChem": true
      },
      {
        "metaRating": 80.90226135952095,
        "chemstyleId": 250,
        "playerRoleId": 44,
        "chemistry": 0,
        "isBestChemstyleAtChem": true
      },
      {
        "metaRating": 95.96742672647375,
        "chemstyleId": 266,
        "playerRoleId": 31,
        "chemistry": 1,
        "isBestChemstyleAtChem": true
      },
      {
        "metaRating": 95.91926732208822,
        "chemstyleId": 266,
        "playerRoleId": 32,
        "chemistry": 1,
        "isBestChemstyleAtChem": true
      },
      {
        "metaRating": 95.35210496533072,
        "chemstyleId": 266,
        "playerRoleId": 35,
        "chemistry": 1,
        "isBestChemstyleAtChem": true
      },
      {
        "metaRating": 95.18852163164689,
        "chemstyleId": 266,
        "playerRoleId": 36,
        "chemistry": 1,
        "isBestChemstyleAtChem": true
      },
      {
        "metaRating": 94.8206368906804,
        "chemstyleId": 266,
        "playerRoleId": 34,
        "chemistry": 1,
        "isBestChemstyleAtChem": true
      },
      {
        "metaRating": 93.70088026736178,
        "chemstyleId": 266,
        "playerRoleId": 43,
        "chemistry": 1,
        "isBestChemstyleAtChem": true
      },
      {
        "metaRating": 93.00854230991257,
        "chemstyleId": 266,
        "playerRoleId": 33,
        "chemistry": 1,
        "isBestChemstyleAtChem": true
      },
      {
        "metaRating": 92.44510488990475,
        "chemstyleId": 266,
        "playerRoleId": 37,
        "chemistry": 1,
        "isBestChemstyleAtChem": true
      },
      {
        "metaRating": 91.75927781519208,
        "chemstyleId": 266,
        "playerRoleId": 41,
        "chemistry": 1,
        "isBestChemstyleAtChem": true
      },
      {
        "metaRating": 90.99685076129512,
        "chemstyleId": 266,
        "playerRoleId": 42,
        "chemistry": 1,
        "isBestChemstyleAtChem": true
      },
      {
        "metaRating": 81.79482381912382,
        "chemstyleId": 255,
        "playerRoleId": 44,
        "chemistry": 1,
        "isBestChemstyleAtChem": true
      },
      {
        "metaRating": 96.5216775953432,
        "chemstyleId": 266,
        "playerRoleId": 32,
        "chemistry": 2,
        "isBestChemstyleAtChem": true
      },
      {
        "metaRating": 96.50701109845929,
        "chemstyleId": 266,
        "playerRoleId": 31,
        "chemistry": 2,
        "isBestChemstyleAtChem": true
      },
      {
        "metaRating": 95.96694536356718,
        "chemstyleId": 266,
        "playerRoleId": 35,
        "chemistry": 2,
        "isBestChemstyleAtChem": true
      },
      {
        "metaRating": 95.78412195651714,
        "chemstyleId": 266,
        "playerRoleId": 36,
        "chemistry": 2,
        "isBestChemstyleAtChem": true
      },
      {
        "metaRating": 95.274567509594,
        "chemstyleId": 266,
        "playerRoleId": 34,
        "chemistry": 2,
        "isBestChemstyleAtChem": true
      },
      {
        "metaRating": 94.26989549699208,
        "chemstyleId": 266,
        "playerRoleId": 43,
        "chemistry": 2,
        "isBestChemstyleAtChem": true
      },
      {
        "metaRating": 93.54264194512889,
        "chemstyleId": 266,
        "playerRoleId": 33,
        "chemistry": 2,
        "isBestChemstyleAtChem": true
      },
      {
        "metaRating": 93.04498201806422,
        "chemstyleId": 266,
        "playerRoleId": 37,
        "chemistry": 2,
        "isBestChemstyleAtChem": true
      },
      {
        "metaRating": 92.67152530892203,
        "chemstyleId": 266,
        "playerRoleId": 41,
        "chemistry": 2,
        "isBestChemstyleAtChem": true
      },
      {
        "metaRating": 91.99427296085389,
        "chemstyleId": 266,
        "playerRoleId": 42,
        "chemistry": 2,
        "isBestChemstyleAtChem": true
      },
      {
        "metaRating": 82.52038024819447,
        "chemstyleId": 255,
        "playerRoleId": 44,
        "chemistry": 2,
        "isBestChemstyleAtChem": true
      },
      {
        "metaRating": 96.97438532344394,
        "chemstyleId": 255,
        "playerRoleId": 32,
        "chemistry": 3,
        "isBestChemstyleAtChem": true
      },
      {
        "metaRating": 96.88756552581859,
        "chemstyleId": 255,
        "playerRoleId": 31,
        "chemistry": 3,
        "isBestChemstyleAtChem": true
      },
      {
        "metaRating": 96.26664547036961,
        "chemstyleId": 266,
        "playerRoleId": 35,
        "chemistry": 3,
        "isBestChemstyleAtChem": true
      },
      {
        "metaRating": 96.11492393059093,
        "chemstyleId": 266,
        "playerRoleId": 36,
        "chemistry": 3,
        "isBestChemstyleAtChem": true
      },
      {
        "metaRating": 95.52232520121701,
        "chemstyleId": 266,
        "playerRoleId": 34,
        "chemistry": 3,
        "isBestChemstyleAtChem": true
      },
      {
        "metaRating": 94.84769612152252,
        "chemstyleId": 255,
        "playerRoleId": 43,
        "chemistry": 3,
        "isBestChemstyleAtChem": true
      },
      {
        "metaRating": 93.81202970023092,
        "chemstyleId": 266,
        "playerRoleId": 33,
        "chemistry": 3,
        "isBestChemstyleAtChem": true
      },
      {
        "metaRating": 93.40529584679197,
        "chemstyleId": 266,
        "playerRoleId": 37,
        "chemistry": 3,
        "isBestChemstyleAtChem": true
      },
      {
        "metaRating": 93.24703334410121,
        "chemstyleId": 266,
        "playerRoleId": 41,
        "chemistry": 3,
        "isBestChemstyleAtChem": true
      },
      {
        "metaRating": 92.60677294386315,
        "chemstyleId": 266,
        "playerRoleId": 42,
        "chemistry": 3,
        "isBestChemstyleAtChem": true
      },
      {
        "metaRating": 83.90061955083245,
        "chemstyleId": 255,
        "playerRoleId": 44,
        "chemistry": 3,
        "isBestChemstyleAtChem": true
      }
    ]
  },
  {
    "archetype": "wide_playmaker",
    "ratings": [
      {
        "metaRating": 95.29622858122168,
        "chemstyleId": 250,
        "playerRoleId": 31,
        "chemistry": 0,
        "isBestChemstyleAtChem": true
      },
      {
        "metaRating": 95.1346647388765,
        "chemstyleId": 250,
        "playerRoleId": 32,
        "chemistry": 0,
        "isBestChemstyleAtChem": true
      },
      {
        "metaRating": 94.52835970099954,
        "chemstyleId": 250,
        "playerRoleId": 35,
        "chemistry": 0,
        "isBestChemstyleAtChem": true
      },
      {
        "metaRating": 94.39162883429915,
        "chemstyleId": 250,
        "playerRoleId": 36,
        "chemistry": 0,
        "isBestChemstyleAtChem": true
      },
      {
        "metaRating": 94.26792501565124,
        "chemstyleId": 250,
        "playerRoleId": 34,
        "chemistry": 0,
        "isBestChemstyleAtChem": true
      },
      {
        "metaRating": 92.94864884709415,
        "chemstyleId": 250,
        "playerRoleId": 43,
        "chemistry": 0,
        "isBestChemstyleAtChem": true
      },
      {
        "metaRating": 92.29464728184834,
        "chemstyleId": 250,
        "playerRoleId": 33,
        "chemistry": 0,
        "isBestChemstyleAtChem": true
      },
      {
        "metaRating": 91.65798619887252,
        "chemstyleId": 250,
        "playerRoleId": 37,
        "chemistry": 0,
        "isBestChemstyleAtChem": true
      },
      {
        "metaRating": 90.62403895878573,
        "chemstyleId": 250,
        "playerRoleId": 41,
        "chemistry": 0,
        "isBestChemstyleAtChem": true
      },
      {
        "metaRating": 89.74730148891554,
        "chemstyleId": 250,
        "playerRoleId": 42,
        "chemistry": 0,
        "isBestChemstyleAtChem": true
      },
      {
        "metaRating": 80.90226135952095,
        "chemstyleId": 250,
        "playerRoleId": 44,
        "chemistry": 0,
        "isBestChemstyleAtChem": true
      },
      {
        "metaRating": 95.96742672647375,
        "chemstyleId": 266,
        "playerRoleId": 31,
        "chemistry": 1,
        "isBestChemstyleAtChem": true
      },
      {
        "metaRating": 95.91926732208822,
        "chemstyleId": 266,
        "playerRoleId": 32,
        "chemistry": 1,
        "isBestChemstyleAtChem": true
      },
      {
        "metaRating": 95.35210496533072,
        "chemstyleId": 266,
        "playerRoleId": 35,
        "chemistry": 1,
        "isBestChemstyleAtChem": true
      },
      {
        "metaRating": 95.18852163164689,
        "chemstyleId": 266,
        "playerRoleId": 36,
        "chemistry": 1,
        "isBestChemstyleAtChem": true
      },
      {
        "metaRating": 94.8206368906804,
        "chemstyleId": 266,
        "playerRoleId": 34,
        "chemistry": 1,
        "isBestChemstyleAtChem": true
      },
      {
        "metaRating": 93.70088026736178,
        "chemstyleId": 266,
        "playerRoleId": 43,
        "chemistry": 1,
        "isBestChemstyleAtChem": true
      },
      {
        "metaRating": 93.00854230991257,
        "chemstyleId": 266,
        "playerRoleId": 33,
        "chemistry": 1,
        "isBestChemstyleAtChem": true
      },
      {
        "metaRating": 92.44510488990475,
        "chemstyleId": 266,
        "playerRoleId": 37,
        "chemistry": 1,
        "isBestChemstyleAtChem": true
      },
      {
        "metaRating": 91.75927781519208,
        "chemstyleId": 266,
        "playerRoleId": 41,
        "chemistry": 1,
        "isBestChemstyleAtChem": true
      },
      {
        "metaRating": 90.99685076129512,
        "chemstyleId": 266,
        "playerRoleId": 42,
        "chemistry": 1,
        "isBestChemstyleAtChem": true
      },
      {
        "metaRating": 81.79482381912382,
        "chemstyleId": 255,
        "playerRoleId": 44,
        "chemistry": 1,
        "isBestChemstyleAtChem": true
      },
      {
        "metaRating": 96.5216775953432,
        "chemstyleId": 266,
        "playerRoleId": 32,
        "chemistry": 2,
        "isBestChemstyleAtChem": true
      },
      {
        "metaRating": 96.50701109845929,
        "chemstyleId": 266,
        "playerRoleId": 31,
        "chemistry": 2,
        "isBestChemstyleAtChem": true
      },
      {
        "metaRating": 95.96694536356718,
        "chemstyleId": 266,
        "playerRoleId": 35,
        "chemistry": 2,
        "isBestChemstyleAtChem": true
      },
      {
        "metaRating": 95.78412195651714,
        "chemstyleId": 266,
        "playerRoleId": 36,
        "chemistry": 2,
        "isBestChemstyleAtChem": true
      },
      {
        "metaRating": 95.274567509594,
        "chemstyleId": 266,
        "playerRoleId": 34,
        "chemistry": 2,
        "isBestChemstyleAtChem": true
      },
      {
        "metaRating": 94.26989549699208,
        "chemstyleId": 266,
        "playerRoleId": 43,
        "chemistry": 2,
        "isBestChemstyleAtChem": true
      },
      {
        "metaRating": 93.54264194512889,
        "chemstyleId": 266,
        "playerRoleId": 33,
        "chemistry": 2,
        "isBestChemstyleAtChem": true
      },
      {
        "metaRating": 93.04498201806422,
        "chemstyleId": 266,
        "playerRoleId": 37,
        "chemistry": 2,
        "isBestChemstyleAtChem": true
      },
      {
        "metaRating": 92.67152530892203,
        "chemstyleId": 266,
        "playerRoleId": 41,
        "chemistry": 2,
        "isBestChemstyleAtChem": true
      },
      {
        "metaRating": 91.99427296085389,
        "chemstyleId": 266,
        "playerRoleId": 42,
        "chemistry": 2,
        "isBestChemstyleAtChem": true
      },
      {
        "metaRating": 82.52038024819447,
        "chemstyleId": 255,
        "playerRoleId": 44,
        "chemistry": 2,
        "isBestChemstyleAtChem": true
      },
      {
        "metaRating": 96.97438532344394,
        "chemstyleId": 255,
        "playerRoleId": 32,
        "chemistry": 3,
        "isBestChemstyleAtChem": true
      },
      {
        "metaRating": 96.88756552581859,
        "chemstyleId": 255,
        "playerRoleId": 31,
        "chemistry": 3,
        "isBestChemstyleAtChem": true
      },
      {
        "metaRating": 96.26664547036961,
        "chemstyleId": 266,
        "playerRoleId": 35,
        "chemistry": 3,
        "isBestChemstyleAtChem": true
      },
      {
        "metaRating": 96.11492393059093,
        "chemstyleId": 266,
        "playerRoleId": 36,
        "chemistry": 3,
        "isBestChemstyleAtChem": true
      },
      {
        "metaRating": 95.52232520121701,
        "chemstyleId": 266,
        "playerRoleId": 34,
        "chemistry": 3,
        "isBestChemstyleAtChem": true
      },
      {
        "metaRating": 94.84769612152252,
        "chemstyleId": 255,
        "playerRoleId": 43,
        "chemistry": 3,
        "isBestChemstyleAtChem": true
      },
      {
        "metaRating": 93.81202970023092,
        "chemstyleId": 266,
        "playerRoleId": 33,
        "chemistry": 3,
        "isBestChemstyleAtChem": true
      },
      {
        "metaRating": 93.40529584679197,
        "chemstyleId": 266,
        "playerRoleId": 37,
        "chemistry": 3,
        "isBestChemstyleAtChem": true
      },
      {
        "metaRating": 93.24703334410121,
        "chemstyleId": 266,
        "playerRoleId": 41,
        "chemistry": 3,
        "isBestChemstyleAtChem": true
      },
      {
        "metaRating": 92.60677294386315,
        "chemstyleId": 266,
        "playerRoleId": 42,
        "chemistry": 3,
        "isBestChemstyleAtChem": true
      },
      {
        "metaRating": 83.90061955083245,
        "chemstyleId": 255,
        "playerRoleId": 44,
        "chemistry": 3,
        "isBestChemstyleAtChem": true
      }
    ]
  },
  {
    "archetype": "advanced_forward",
    "ratings": [
      {
        "metaRating": 95.29622858122168,
        "chemstyleId": 250,
        "playerRoleId": 31,
        "chemistry": 0,
        "isBestChemstyleAtChem": true
      },
      {
        "metaRating": 95.1346647388765,
        "chemstyleId": 250,
        "playerRoleId": 32,
        "chemistry": 0,
        "isBestChemstyleAtChem": true
      },
      {
        "metaRating": 94.52835970099954,
        "chemstyleId": 250,
        "playerRoleId": 35,
        "chemistry": 0,
        "isBestChemstyleAtChem": true
      },
      {
        "metaRating": 94.39162883429915,
        "chemstyleId": 250,
        "playerRoleId": 36,
        "chemistry": 0,
        "isBestChemstyleAtChem": true
      },
      {
        "metaRating": 94.26792501565124,
        "chemstyleId": 250,
        "playerRoleId": 34,
        "chemistry": 0,
        "isBestChemstyleAtChem": true
      },
      {
        "metaRating": 92.94864884709415,
        "chemstyleId": 250,
        "playerRoleId": 43,
        "chemistry": 0,
        "isBestChemstyleAtChem": true
      },
      {
        "metaRating": 92.29464728184834,
        "chemstyleId": 250,
        "playerRoleId": 33,
        "chemistry": 0,
        "isBestChemstyleAtChem": true
      },
      {
        "metaRating": 91.65798619887252,
        "chemstyleId": 250,
        "playerRoleId": 37,
        "chemistry": 0,
        "isBestChemstyleAtChem": true
      },
      {
        "metaRating": 90.62403895878573,
        "chemstyleId": 250,
        "playerRoleId": 41,
        "chemistry": 0,
        "isBestChemstyleAtChem": true
      },
      {
        "metaRating": 89.74730148891554,
        "chemstyleId": 250,
        "playerRoleId": 42,
        "chemistry": 0,
        "isBestChemstyleAtChem": true
      },
      {
        "metaRating": 80.90226135952095,
        "chemstyleId": 250,
        "playerRoleId": 44,
        "chemistry": 0,
        "isBestChemstyleAtChem": true
      },
      {
        "metaRating": 95.96742672647375,
        "chemstyleId": 266,
        "playerRoleId": 31,
        "chemistry": 1,
        "isBestChemstyleAtChem": true
      },
      {
        "metaRating": 95.91926732208822,
        "chemstyleId": 266,
        "playerRoleId": 32,
        "chemistry": 1,
        "isBestChemstyleAtChem": true
      },
      {
        "metaRating": 95.35210496533072,
        "chemstyleId": 266,
        "playerRoleId": 35,
        "chemistry": 1,
        "isBestChemstyleAtChem": true
      },
      {
        "metaRating": 95.18852163164689,
        "chemstyleId": 266,
        "playerRoleId": 36,
        "chemistry": 1,
        "isBestChemstyleAtChem": true
      },
      {
        "metaRating": 94.8206368906804,
        "chemstyleId": 266,
        "playerRoleId": 34,
        "chemistry": 1,
        "isBestChemstyleAtChem": true
      },
      {
        "metaRating": 93.70088026736178,
        "chemstyleId": 266,
        "playerRoleId": 43,
        "chemistry": 1,
        "isBestChemstyleAtChem": true
      },
      {
        "metaRating": 93.00854230991257,
        "chemstyleId": 266,
        "playerRoleId": 33,
        "chemistry": 1,
        "isBestChemstyleAtChem": true
      },
      {
        "metaRating": 92.44510488990475,
        "chemstyleId": 266,
        "playerRoleId": 37,
        "chemistry": 1,
        "isBestChemstyleAtChem": true
      },
      {
        "metaRating": 91.75927781519208,
        "chemstyleId": 266,
        "playerRoleId": 41,
        "chemistry": 1,
        "isBestChemstyleAtChem": true
      },
      {
        "metaRating": 90.99685076129512,
        "chemstyleId": 266,
        "playerRoleId": 42,
        "chemistry": 1,
        "isBestChemstyleAtChem": true
      },
      {
        "metaRating": 81.79482381912382,
        "chemstyleId": 255,
        "playerRoleId": 44,
        "chemistry": 1,
        "isBestChemstyleAtChem": true
      },
      {
        "metaRating": 96.5216775953432,
        "chemstyleId": 266,
        "playerRoleId": 32,
        "chemistry": 2,
        "isBestChemstyleAtChem": true
      },
      {
        "metaRating": 96.50701109845929,
        "chemstyleId": 266,
        "playerRoleId": 31,
        "chemistry": 2,
        "isBestChemstyleAtChem": true
      },
      {
        "metaRating": 95.96694536356718,
        "chemstyleId": 266,
        "playerRoleId": 35,
        "chemistry": 2,
        "isBestChemstyleAtChem": true
      },
      {
        "metaRating": 95.78412195651714,
        "chemstyleId": 266,
        "playerRoleId": 36,
        "chemistry": 2,
        "isBestChemstyleAtChem": true
      },
      {
        "metaRating": 95.274567509594,
        "chemstyleId": 266,
        "playerRoleId": 34,
        "chemistry": 2,
        "isBestChemstyleAtChem": true
      },
      {
        "metaRating": 94.26989549699208,
        "chemstyleId": 266,
        "playerRoleId": 43,
        "chemistry": 2,
        "isBestChemstyleAtChem": true
      },
      {
        "metaRating": 93.54264194512889,
        "chemstyleId": 266,
        "playerRoleId": 33,
        "chemistry": 2,
        "isBestChemstyleAtChem": true
      },
      {
        "metaRating": 93.04498201806422,
        "chemstyleId": 266,
        "playerRoleId": 37,
        "chemistry": 2,
        "isBestChemstyleAtChem": true
      },
      {
        "metaRating": 92.67152530892203,
        "chemstyleId": 266,
        "playerRoleId": 41,
        "chemistry": 2,
        "isBestChemstyleAtChem": true
      },
      {
        "metaRating": 91.99427296085389,
        "chemstyleId": 266,
        "playerRoleId": 42,
        "chemistry": 2,
        "isBestChemstyleAtChem": true
      },
      {
        "metaRating": 82.52038024819447,
        "chemstyleId": 255,
        "playerRoleId": 44,
        "chemistry": 2,
        "isBestChemstyleAtChem": true
      },
      {
        "metaRating": 96.97438532344394,
        "chemstyleId": 255,
        "playerRoleId": 32,
        "chemistry": 3,
        "isBestChemstyleAtChem": true
      },
      {
        "metaRating": 96.88756552581859,
        "chemstyleId": 255,
        "playerRoleId": 31,
        "chemistry": 3,
        "isBestChemstyleAtChem": true
      },
      {
        "metaRating": 96.26664547036961,
        "chemstyleId": 266,
        "playerRoleId": 35,
        "chemistry": 3,
        "isBestChemstyleAtChem": true
      },
      {
        "metaRating": 96.11492393059093,
        "chemstyleId": 266,
        "playerRoleId": 36,
        "chemistry": 3,
        "isBestChemstyleAtChem": true
      },
      {
        "metaRating": 95.52232520121701,
        "chemstyleId": 266,
        "playerRoleId": 34,
        "chemistry": 3,
        "isBestChemstyleAtChem": true
      },
      {
        "metaRating": 94.84769612152252,
        "chemstyleId": 255,
        "playerRoleId": 43,
        "chemistry": 3,
        "isBestChemstyleAtChem": true
      },
      {
        "metaRating": 93.81202970023092,
        "chemstyleId": 266,
        "playerRoleId": 33,
        "chemistry": 3,
        "isBestChemstyleAtChem": true
      },
      {
        "metaRating": 93.40529584679197,
        "chemstyleId": 266,
        "playerRoleId": 37,
        "chemistry": 3,
        "isBestChemstyleAtChem": true
      },
      {
        "metaRating": 93.24703334410121,
        "chemstyleId": 266,
        "playerRoleId": 41,
        "chemistry": 3,
        "isBestChemstyleAtChem": true
      },
      {
        "metaRating": 92.60677294386315,
        "chemstyleId": 266,
        "playerRoleId": 42,
        "chemistry": 3,
        "isBestChemstyleAtChem": true
      },
      {
        "metaRating": 83.90061955083245,
        "chemstyleId": 255,
        "playerRoleId": 44,
        "chemistry": 3,
        "isBestChemstyleAtChem": true
      }
    ]
  },
  {
    "archetype": "target_forward",
    "ratings": [
      {
        "metaRating": 95.29622858122168,
        "chemstyleId": 250,
        "playerRoleId": 31,
        "chemistry": 0,
        "isBestChemstyleAtChem": true
      },
      {
        "metaRating": 95.1346647388765,
        "chemstyleId": 250,
        "playerRoleId": 32,
        "chemistry": 0,
        "isBestChemstyleAtChem": true
      },
      {
        "metaRating": 94.52835970099954,
        "chemstyleId": 250,
        "playerRoleId": 35,
        "chemistry": 0,
        "isBestChemstyleAtChem": true
      },
      {
        "metaRating": 94.39162883429915,
        "chemstyleId": 250,
        "playerRoleId": 36,
        "chemistry": 0,
        "isBestChemstyleAtChem": true
      },
      {
        "metaRating": 94.26792501565124,
        "chemstyleId": 250,
        "playerRoleId": 34,
        "chemistry": 0,
        "isBestChemstyleAtChem": true
      },
      {
        "metaRating": 92.94864884709415,
        "chemstyleId": 250,
        "playerRoleId": 43,
        "chemistry": 0,
        "isBestChemstyleAtChem": true
      },
      {
        "metaRating": 92.29464728184834,
        "chemstyleId": 250,
        "playerRoleId": 33,
        "chemistry": 0,
        "isBestChemstyleAtChem": true
      },
      {
        "metaRating": 91.65798619887252,
        "chemstyleId": 250,
        "playerRoleId": 37,
        "chemistry": 0,
        "isBestChemstyleAtChem": true
      },
      {
        "metaRating": 90.62403895878573,
        "chemstyleId": 250,
        "playerRoleId": 41,
        "chemistry": 0,
        "isBestChemstyleAtChem": true
      },
      {
        "metaRating": 89.74730148891554,
        "chemstyleId": 250,
        "playerRoleId": 42,
        "chemistry": 0,
        "isBestChemstyleAtChem": true
      },
      {
        "metaRating": 80.90226135952095,
        "chemstyleId": 250,
        "playerRoleId": 44,
        "chemistry": 0,
        "isBestChemstyleAtChem": true
      },
      {
        "metaRating": 95.96742672647375,
        "chemstyleId": 266,
        "playerRoleId": 31,
        "chemistry": 1,
        "isBestChemstyleAtChem": true
      },
      {
        "metaRating": 95.91926732208822,
        "chemstyleId": 266,
        "playerRoleId": 32,
        "chemistry": 1,
        "isBestChemstyleAtChem": true
      },
      {
        "metaRating": 95.35210496533072,
        "chemstyleId": 266,
        "playerRoleId": 35,
        "chemistry": 1,
        "isBestChemstyleAtChem": true
      },
      {
        "metaRating": 95.18852163164689,
        "chemstyleId": 266,
        "playerRoleId": 36,
        "chemistry": 1,
        "isBestChemstyleAtChem": true
      },
      {
        "metaRating": 94.8206368906804,
        "chemstyleId": 266,
        "playerRoleId": 34,
        "chemistry": 1,
        "isBestChemstyleAtChem": true
      },
      {
        "metaRating": 93.70088026736178,
        "chemstyleId": 266,
        "playerRoleId": 43,
        "chemistry": 1,
        "isBestChemstyleAtChem": true
      },
      {
        "metaRating": 93.00854230991257,
        "chemstyleId": 266,
        "playerRoleId": 33,
        "chemistry": 1,
        "isBestChemstyleAtChem": true
      },
      {
        "metaRating": 92.44510488990475,
        "chemstyleId": 266,
        "playerRoleId": 37,
        "chemistry": 1,
        "isBestChemstyleAtChem": true
      },
      {
        "metaRating": 91.75927781519208,
        "chemstyleId": 266,
        "playerRoleId": 41,
        "chemistry": 1,
        "isBestChemstyleAtChem": true
      },
      {
        "metaRating": 90.99685076129512,
        "chemstyleId": 266,
        "playerRoleId": 42,
        "chemistry": 1,
        "isBestChemstyleAtChem": true
      },
      {
        "metaRating": 81.79482381912382,
        "chemstyleId": 255,
        "playerRoleId": 44,
        "chemistry": 1,
        "isBestChemstyleAtChem": true
      },
      {
        "metaRating": 96.5216775953432,
        "chemstyleId": 266,
        "playerRoleId": 32,
        "chemistry": 2,
        "isBestChemstyleAtChem": true
      },
      {
        "metaRating": 96.50701109845929,
        "chemstyleId": 266,
        "playerRoleId": 31,
        "chemistry": 2,
        "isBestChemstyleAtChem": true
      },
      {
        "metaRating": 95.96694536356718,
        "chemstyleId": 266,
        "playerRoleId": 35,
        "chemistry": 2,
        "isBestChemstyleAtChem": true
      },
      {
        "metaRating": 95.78412195651714,
        "chemstyleId": 266,
        "playerRoleId": 36,
        "chemistry": 2,
        "isBestChemstyleAtChem": true
      },
      {
        "metaRating": 95.274567509594,
        "chemstyleId": 266,
        "playerRoleId": 34,
        "chemistry": 2,
        "isBestChemstyleAtChem": true
      },
      {
        "metaRating": 94.26989549699208,
        "chemstyleId": 266,
        "playerRoleId": 43,
        "chemistry": 2,
        "isBestChemstyleAtChem": true
      },
      {
        "metaRating": 93.54264194512889,
        "chemstyleId": 266,
        "playerRoleId": 33,
        "chemistry": 2,
        "isBestChemstyleAtChem": true
      },
      {
        "metaRating": 93.04498201806422,
        "chemstyleId": 266,
        "playerRoleId": 37,
        "chemistry": 2,
        "isBestChemstyleAtChem": true
      },
      {
        "metaRating": 92.67152530892203,
        "chemstyleId": 266,
        "playerRoleId": 41,
        "chemistry": 2,
        "isBestChemstyleAtChem": true
      },
      {
        "metaRating": 91.99427296085389,
        "chemstyleId": 266,
        "playerRoleId": 42,
        "chemistry": 2,
        "isBestChemstyleAtChem": true
      },
      {
        "metaRating": 82.52038024819447,
        "chemstyleId": 255,
        "playerRoleId": 44,
        "chemistry": 2,
        "isBestChemstyleAtChem": true
      },
      {
        "metaRating": 96.97438532344394,
        "chemstyleId": 255,
        "playerRoleId": 32,
        "chemistry": 3,
        "isBestChemstyleAtChem": true
      },
      {
        "metaRating": 96.88756552581859,
        "chemstyleId": 255,
        "playerRoleId": 31,
        "chemistry": 3,
        "isBestChemstyleAtChem": true
      },
      {
        "metaRating": 96.26664547036961,
        "chemstyleId": 266,
        "playerRoleId": 35,
        "chemistry": 3,
        "isBestChemstyleAtChem": true
      },
      {
        "metaRating": 96.11492393059093,
        "chemstyleId": 266,
        "playerRoleId": 36,
        "chemistry": 3,
        "isBestChemstyleAtChem": true
      },
      {
        "metaRating": 95.52232520121701,
        "chemstyleId": 266,
        "playerRoleId": 34,
        "chemistry": 3,
        "isBestChemstyleAtChem": true
      },
      {
        "metaRating": 94.84769612152252,
        "chemstyleId": 255,
        "playerRoleId": 43,
        "chemistry": 3,
        "isBestChemstyleAtChem": true
      },
      {
        "metaRating": 93.81202970023092,
        "chemstyleId": 266,
        "playerRoleId": 33,
        "chemistry": 3,
        "isBestChemstyleAtChem": true
      },
      {
        "metaRating": 93.40529584679197,
        "chemstyleId": 266,
        "playerRoleId": 37,
        "chemistry": 3,
        "isBestChemstyleAtChem": true
      },
      {
        "metaRating": 93.24703334410121,
        "chemstyleId": 266,
        "playerRoleId": 41,
        "chemistry": 3,
        "isBestChemstyleAtChem": true
      },
      {
        "metaRating": 92.60677294386315,
        "chemstyleId": 266,
        "playerRoleId": 42,
        "chemistry": 3,
        "isBestChemstyleAtChem": true
      },
      {
        "metaRating": 83.90061955083245,
        "chemstyleId": 255,
        "playerRoleId": 44,
        "chemistry": 3,
        "isBestChemstyleAtChem": true
      }
    ]
  },
  {
    "archetype": "poacher",
    "ratings": [
      {
        "metaRating": 95.29622858122168,
        "chemstyleId": 250,
        "playerRoleId": 31,
        "chemistry": 0,
        "isBestChemstyleAtChem": true
      },
      {
        "metaRating": 95.1346647388765,
        "chemstyleId": 250,
        "playerRoleId": 32,
        "chemistry": 0,
        "isBestChemstyleAtChem": true
      },
      {
        "metaRating": 94.52835970099954,
        "chemstyleId": 250,
        "playerRoleId": 35,
        "chemistry": 0,
        "isBestChemstyleAtChem": true
      },
      {
        "metaRating": 94.39162883429915,
        "chemstyleId": 250,
        "playerRoleId": 36,
        "chemistry": 0,
        "isBestChemstyleAtChem": true
      },
      {
        "metaRating": 94.26792501565124,
        "chemstyleId": 250,
        "playerRoleId": 34,
        "chemistry": 0,
        "isBestChemstyleAtChem": true
      },
      {
        "metaRating": 92.94864884709415,
        "chemstyleId": 250,
        "playerRoleId": 43,
        "chemistry": 0,
        "isBestChemstyleAtChem": true
      },
      {
        "metaRating": 92.29464728184834,
        "chemstyleId": 250,
        "playerRoleId": 33,
        "chemistry": 0,
        "isBestChemstyleAtChem": true
      },
      {
        "metaRating": 91.65798619887252,
        "chemstyleId": 250,
        "playerRoleId": 37,
        "chemistry": 0,
        "isBestChemstyleAtChem": true
      },
      {
        "metaRating": 90.62403895878573,
        "chemstyleId": 250,
        "playerRoleId": 41,
        "chemistry": 0,
        "isBestChemstyleAtChem": true
      },
      {
        "metaRating": 89.74730148891554,
        "chemstyleId": 250,
        "playerRoleId": 42,
        "chemistry": 0,
        "isBestChemstyleAtChem": true
      },
      {
        "metaRating": 80.90226135952095,
        "chemstyleId": 250,
        "playerRoleId": 44,
        "chemistry": 0,
        "isBestChemstyleAtChem": true
      },
      {
        "metaRating": 95.96742672647375,
        "chemstyleId": 266,
        "playerRoleId": 31,
        "chemistry": 1,
        "isBestChemstyleAtChem": true
      },
      {
        "metaRating": 95.91926732208822,
        "chemstyleId": 266,
        "playerRoleId": 32,
        "chemistry": 1,
        "isBestChemstyleAtChem": true
      },
      {
        "metaRating": 95.35210496533072,
        "chemstyleId": 266,
        "playerRoleId": 35,
        "chemistry": 1,
        "isBestChemstyleAtChem": true
      },
      {
        "metaRating": 95.18852163164689,
        "chemstyleId": 266,
        "playerRoleId": 36,
        "chemistry": 1,
        "isBestChemstyleAtChem": true
      },
      {
        "metaRating": 94.8206368906804,
        "chemstyleId": 266,
        "playerRoleId": 34,
        "chemistry": 1,
        "isBestChemstyleAtChem": true
      },
      {
        "metaRating": 93.70088026736178,
        "chemstyleId": 266,
        "playerRoleId": 43,
        "chemistry": 1,
        "isBestChemstyleAtChem": true
      },
      {
        "metaRating": 93.00854230991257,
        "chemstyleId": 266,
        "playerRoleId": 33,
        "chemistry": 1,
        "isBestChemstyleAtChem": true
      },
      {
        "metaRating": 92.44510488990475,
        "chemstyleId": 266,
        "playerRoleId": 37,
        "chemistry": 1,
        "isBestChemstyleAtChem": true
      },
      {
        "metaRating": 91.75927781519208,
        "chemstyleId": 266,
        "playerRoleId": 41,
        "chemistry": 1,
        "isBestChemstyleAtChem": true
      },
      {
        "metaRating": 90.99685076129512,
        "chemstyleId": 266,
        "playerRoleId": 42,
        "chemistry": 1,
        "isBestChemstyleAtChem": true
      },
      {
        "metaRating": 81.79482381912382,
        "chemstyleId": 255,
        "playerRoleId": 44,
        "chemistry": 1,
        "isBestChemstyleAtChem": true
      },
      {
        "metaRating": 96.5216775953432,
        "chemstyleId": 266,
        "playerRoleId": 32,
        "chemistry": 2,
        "isBestChemstyleAtChem": true
      },
      {
        "metaRating": 96.50701109845929,
        "chemstyleId": 266,
        "playerRoleId": 31,
        "chemistry": 2,
        "isBestChemstyleAtChem": true
      },
      {
        "metaRating": 95.96694536356718,
        "chemstyleId": 266,
        "playerRoleId": 35,
        "chemistry": 2,
        "isBestChemstyleAtChem": true
      },
      {
        "metaRating": 95.78412195651714,
        "chemstyleId": 266,
        "playerRoleId": 36,
        "chemistry": 2,
        "isBestChemstyleAtChem": true
      },
      {
        "metaRating": 95.274567509594,
        "chemstyleId": 266,
        "playerRoleId": 34,
        "chemistry": 2,
        "isBestChemstyleAtChem": true
      },
      {
        "metaRating": 94.26989549699208,
        "chemstyleId": 266,
        "playerRoleId": 43,
        "chemistry": 2,
        "isBestChemstyleAtChem": true
      },
      {
        "metaRating": 93.54264194512889,
        "chemstyleId": 266,
        "playerRoleId": 33,
        "chemistry": 2,
        "isBestChemstyleAtChem": true
      },
      {
        "metaRating": 93.04498201806422,
        "chemstyleId": 266,
        "playerRoleId": 37,
        "chemistry": 2,
        "isBestChemstyleAtChem": true
      },
      {
        "metaRating": 92.67152530892203,
        "chemstyleId": 266,
        "playerRoleId": 41,
        "chemistry": 2,
        "isBestChemstyleAtChem": true
      },
      {
        "metaRating": 91.99427296085389,
        "chemstyleId": 266,
        "playerRoleId": 42,
        "chemistry": 2,
        "isBestChemstyleAtChem": true
      },
      {
        "metaRating": 82.52038024819447,
        "chemstyleId": 255,
        "playerRoleId": 44,
        "chemistry": 2,
        "isBestChemstyleAtChem": true
      },
      {
        "metaRating": 96.97438532344394,
        "chemstyleId": 255,
        "playerRoleId": 32,
        "chemistry": 3,
        "isBestChemstyleAtChem": true
      },
      {
        "metaRating": 96.88756552581859,
        "chemstyleId": 255,
        "playerRoleId": 31,
        "chemistry": 3,
        "isBestChemstyleAtChem": true
      },
      {
        "metaRating": 96.26664547036961,
        "chemstyleId": 266,
        "playerRoleId": 35,
        "chemistry": 3,
        "isBestChemstyleAtChem": true
      },
      {
        "metaRating": 96.11492393059093,
        "chemstyleId": 266,
        "playerRoleId": 36,
        "chemistry": 3,
        "isBestChemstyleAtChem": true
      },
      {
        "metaRating": 95.52232520121701,
        "chemstyleId": 266,
        "playerRoleId": 34,
        "chemistry": 3,
        "isBestChemstyleAtChem": true
      },
      {
        "metaRating": 94.84769612152252,
        "chemstyleId": 255,
        "playerRoleId": 43,
        "chemistry": 3,
        "isBestChemstyleAtChem": true
      },
      {
        "metaRating": 93.81202970023092,
        "chemstyleId": 266,
        "playerRoleId": 33,
        "chemistry": 3,
        "isBestChemstyleAtChem": true
      },
      {
        "metaRating": 93.40529584679197,
        "chemstyleId": 266,
        "playerRoleId": 37,
        "chemistry": 3,
        "isBestChemstyleAtChem": true
      },
      {
        "metaRating": 93.24703334410121,
        "chemstyleId": 266,
        "playerRoleId": 41,
        "chemistry": 3,
        "isBestChemstyleAtChem": true
      },
      {
        "metaRating": 92.60677294386315,
        "chemstyleId": 266,
        "playerRoleId": 42,
        "chemistry": 3,
        "isBestChemstyleAtChem": true
      },
      {
        "metaRating": 83.90061955083245,
        "chemstyleId": 255,
        "playerRoleId": 44,
        "chemistry": 3,
        "isBestChemstyleAtChem": true
      }
    ]
  },
  {
    "archetype": "false_nine",
    "ratings": [
      {
        "metaRating": 95.29622858122168,
        "chemstyleId": 250,
        "playerRoleId": 31,
        "chemistry": 0,
        "isBestChemstyleAtChem": true
      },
      {
        "metaRating": 95.1346647388765,
        "chemstyleId": 250,
        "playerRoleId": 32,
        "chemistry": 0,
        "isBestChemstyleAtChem": true
      },
      {
        "metaRating": 94.52835970099954,
        "chemstyleId": 250,
        "playerRoleId": 35,
        "chemistry": 0,
        "isBestChemstyleAtChem": true
      },
      {
        "metaRating": 94.39162883429915,
        "chemstyleId": 250,
        "playerRoleId": 36,
        "chemistry": 0,
        "isBestChemstyleAtChem": true
      },
      {
        "metaRating": 94.26792501565124,
        "chemstyleId": 250,
        "playerRoleId": 34,
        "chemistry": 0,
        "isBestChemstyleAtChem": true
      },
      {
        "metaRating": 92.94864884709415,
        "chemstyleId": 250,
        "playerRoleId": 43,
        "chemistry": 0,
        "isBestChemstyleAtChem": true
      },
      {
        "metaRating": 92.29464728184834,
        "chemstyleId": 250,
        "playerRoleId": 33,
        "chemistry": 0,
        "isBestChemstyleAtChem": true
      },
      {
        "metaRating": 91.65798619887252,
        "chemstyleId": 250,
        "playerRoleId": 37,
        "chemistry": 0,
        "isBestChemstyleAtChem": true
      },
      {
        "metaRating": 90.62403895878573,
        "chemstyleId": 250,
        "playerRoleId": 41,
        "chemistry": 0,
        "isBestChemstyleAtChem": true
      },
      {
        "metaRating": 89.74730148891554,
        "chemstyleId": 250,
        "playerRoleId": 42,
        "chemistry": 0,
        "isBestChemstyleAtChem": true
      },
      {
        "metaRating": 80.90226135952095,
        "chemstyleId": 250,
        "playerRoleId": 44,
        "chemistry": 0,
        "isBestChemstyleAtChem": true
      },
      {
        "metaRating": 95.96742672647375,
        "chemstyleId": 266,
        "playerRoleId": 31,
        "chemistry": 1,
        "isBestChemstyleAtChem": true
      },
      {
        "metaRating": 95.91926732208822,
        "chemstyleId": 266,
        "playerRoleId": 32,
        "chemistry": 1,
        "isBestChemstyleAtChem": true
      },
      {
        "metaRating": 95.35210496533072,
        "chemstyleId": 266,
        "playerRoleId": 35,
        "chemistry": 1,
        "isBestChemstyleAtChem": true
      },
      {
        "metaRating": 95.18852163164689,
        "chemstyleId": 266,
        "playerRoleId": 36,
        "chemistry": 1,
        "isBestChemstyleAtChem": true
      },
      {
        "metaRating": 94.8206368906804,
        "chemstyleId": 266,
        "playerRoleId": 34,
        "chemistry": 1,
        "isBestChemstyleAtChem": true
      },
      {
        "metaRating": 93.70088026736178,
        "chemstyleId": 266,
        "playerRoleId": 43,
        "chemistry": 1,
        "isBestChemstyleAtChem": true
      },
      {
        "metaRating": 93.00854230991257,
        "chemstyleId": 266,
        "playerRoleId": 33,
        "chemistry": 1,
        "isBestChemstyleAtChem": true
      },
      {
        "metaRating": 92.44510488990475,
        "chemstyleId": 266,
        "playerRoleId": 37,
        "chemistry": 1,
        "isBestChemstyleAtChem": true
      },
      {
        "metaRating": 91.75927781519208,
        "chemstyleId": 266,
        "playerRoleId": 41,
        "chemistry": 1,
        "isBestChemstyleAtChem": true
      },
      {
        "metaRating": 90.99685076129512,
        "chemstyleId": 266,
        "playerRoleId": 42,
        "chemistry": 1,
        "isBestChemstyleAtChem": true
      },
      {
        "metaRating": 81.79482381912382,
        "chemstyleId": 255,
        "playerRoleId": 44,
        "chemistry": 1,
        "isBestChemstyleAtChem": true
      },
      {
        "metaRating": 96.5216775953432,
        "chemstyleId": 266,
        "playerRoleId": 32,
        "chemistry": 2,
        "isBestChemstyleAtChem": true
      },
      {
        "metaRating": 96.50701109845929,
        "chemstyleId": 266,
        "playerRoleId": 31,
        "chemistry": 2,
        "isBestChemstyleAtChem": true
      },
      {
        "metaRating": 95.96694536356718,
        "chemstyleId": 266,
        "playerRoleId": 35,
        "chemistry": 2,
        "isBestChemstyleAtChem": true
      },
      {
        "metaRating": 95.78412195651714,
        "chemstyleId": 266,
        "playerRoleId": 36,
        "chemistry": 2,
        "isBestChemstyleAtChem": true
      },
      {
        "metaRating": 95.274567509594,
        "chemstyleId": 266,
        "playerRoleId": 34,
        "chemistry": 2,
        "isBestChemstyleAtChem": true
      },
      {
        "metaRating": 94.26989549699208,
        "chemstyleId": 266,
        "playerRoleId": 43,
        "chemistry": 2,
        "isBestChemstyleAtChem": true
      },
      {
        "metaRating": 93.54264194512889,
        "chemstyleId": 266,
        "playerRoleId": 33,
        "chemistry": 2,
        "isBestChemstyleAtChem": true
      },
      {
        "metaRating": 93.04498201806422,
        "chemstyleId": 266,
        "playerRoleId": 37,
        "chemistry": 2,
        "isBestChemstyleAtChem": true
      },
      {
        "metaRating": 92.67152530892203,
        "chemstyleId": 266,
        "playerRoleId": 41,
        "chemistry": 2,
        "isBestChemstyleAtChem": true
      },
      {
        "metaRating": 91.99427296085389,
        "chemstyleId": 266,
        "playerRoleId": 42,
        "chemistry": 2,
        "isBestChemstyleAtChem": true
      },
      {
        "metaRating": 82.52038024819447,
        "chemstyleId": 255,
        "playerRoleId": 44,
        "chemistry": 2,
        "isBestChemstyleAtChem": true
      },
      {
        "metaRating": 96.97438532344394,
        "chemstyleId": 255,
        "playerRoleId": 32,
        "chemistry": 3,
        "isBestChemstyleAtChem": true
      },
      {
        "metaRating": 96.88756552581859,
        "chemstyleId": 255,
        "playerRoleId": 31,
        "chemistry": 3,
        "isBestChemstyleAtChem": true
      },
      {
        "metaRating": 96.26664547036961,
        "chemstyleId": 266,
        "playerRoleId": 35,
        "chemistry": 3,
        "isBestChemstyleAtChem": true
      },
      {
        "metaRating": 96.11492393059093,
        "chemstyleId": 266,
        "playerRoleId": 36,
        "chemistry": 3,
        "isBestChemstyleAtChem": true
      },
      {
        "metaRating": 95.52232520121701,
        "chemstyleId": 266,
        "playerRoleId": 34,
        "chemistry": 3,
        "isBestChemstyleAtChem": true
      },
      {
        "metaRating": 94.84769612152252,
        "chemstyleId": 255,
        "playerRoleId": 43,
        "chemistry": 3,
        "isBestChemstyleAtChem": true
      },
      {
        "metaRating": 93.81202970023092,
        "chemstyleId": 266,
        "playerRoleId": 33,
        "chemistry": 3,
        "isBestChemstyleAtChem": true
      },
      {
        "metaRating": 93.40529584679197,
        "chemstyleId": 266,
        "playerRoleId": 37,
        "chemistry": 3,
        "isBestChemstyleAtChem": true
      },
      {
        "metaRating": 93.24703334410121,
        "chemstyleId": 266,
        "playerRoleId": 41,
        "chemistry": 3,
        "isBestChemstyleAtChem": true
      },
      {
        "metaRating": 92.60677294386315,
        "chemstyleId": 266,
        "playerRoleId": 42,
        "chemistry": 3,
        "isBestChemstyleAtChem": true
      },
      {
        "metaRating": 83.90061955083245,
        "chemstyleId": 255,
        "playerRoleId": 44,
        "chemistry": 3,
        "isBestChemstyleAtChem": true
      }
    ]
  }
]