[
  {
    "archetype": "holding",
    "ratings": [
      {
        "metaRating": 51.11003553026825,
        "chemstyleId": 250,
        "playerRoleId": 21,
        "chemistry": 0,
        "isBestChemstyleAtChem": true
      },
      {
        "metaRating": 49.66934120297338,
        "chemstyleId": 250,
        "playerRoleId": 16,
        "chemistry": 0,
        "isBestChemstyleAtChem": true
      },
      {
        "metaRating": 48.65603685465263,
        "chemstyleId": 250,
        "playerRoleId": 20,
        "chemistry": 0,
        "isBestChemstyleAtChem": true
      },
      {
        "metaRating": 47.45443692803328,
        "chemstyleId": 250,
        "playerRoleId": 22,
        "chemistry": 0,
        "isBestChemstyleAtChem": true
      },
      {
        "metaRating": 46.9165626504565,
        "chemstyleId": 250,
        "playerRoleId": 18,
        "chemistry": 0,
        "isBestChemstyleAtChem": true
      },
      {
        "metaRating": 42.535539433525976,
        "chemstyleId": 250,
        "playerRoleId": 15,
        "chemistry": 0,
        "isBestChemstyleAtChem": true
      },
      {
        "metaRating": 38.94279345318798,
        "chemstyleId": 250,
        "playerRoleId": 19,
        "chemistry": 0,
        "isBestChemstyleAtChem": true
      },
      {
        "metaRating": 38.3207234480641,
        "chemstyleId": 250,
        "playerRoleId": 14,
        "chemistry": 0,
        "isBestChemstyleAtChem": true
      },
      {
        "metaRating": 34.26378987183497,
        "chemstyleId": 250,
        "playerRoleId": 17,
        "chemistry": 0,
        "isBestChemstyleAtChem": true
      },
      {
        "metaRating": 52.12665880334177,
        "chemstyleId": 260,
        "playerRoleId": 21,
        "chemistry": 1,
        "isBestChemstyleAtChem": true
      },
      {
        "metaRating": 50.86740913743699,
        "chemstyleId": 268,
        "playerRoleId": 16,
        "chemistry": 1,
        "isBestChemstyleAtChem": true
      },
      {
        "metaRating": 49.82204752021474,
        "chemstyleId": 268,
        "playerRoleId": 20,
        "chemistry": 1,
        "isBestChemstyleAtChem": true
      },
      {
        "metaRating": 48.61132389243642,
        "chemstyleId": 267,
        "playerRoleId": 22,
        "chemistry": 1,
        "isBestChemstyleAtChem": true
      },
      {
        "metaRating": 48.10859888785463,
        "chemstyleId": 268,
        "playerRoleId": 18,
        "chemistry": 1,
        "isBestChemstyleAtChem": true
      },
      {
        "metaRating": 44.12073592370013,
        "chemstyleId": 268,
        "playerRoleId": 15,
        "chemistry": 1,
        "isBestChemstyleAtChem": true
      },
      {
        "metaRating": 40.5806841280159,
        "chemstyleId": 268,
        "playerRoleId": 19,
        "chemistry": 1,
        "isBestChemstyleAtChem": true
      },
      {
        "metaRating": 39.984223494336035,
        "chemstyleId": 268,
        "playerRoleId": 14,
        "chemistry": 1,
        "isBestChemstyleAtChem": true
      },
      {
        "metaRating": 36.047847942317425,
        "chemstyleId": 268,
        "playerRoleId": 17,
        "chemistry": 1,
        "isBestChemstyleAtChem": true
      },
      {
        "metaRating": 53.35392570023669,
        "chemstyleId": 262,
        "playerRoleId": 21,
        "chemistry": 2,
        "isBestChemstyleAtChem": true
      },
      {
        "metaRating": 52.37307527742976,
        "chemstyleId": 262,
        "playerRoleId": 16,
        "chemistry": 2,
        "isBestChemstyleAtChem": true
      },
      {
        "metaRating": 51.335058373085516,
        "chemstyleId": 262,
        "playerRoleId": 20,
        "chemistry": 2,
        "isBestChemstyleAtChem": true
      },
      {
        "metaRating": 49.81173204908924,
        "chemstyleId": 267,
        "playerRoleId": 22,
        "chemistry": 2,
        "isBestChemstyleAtChem": true
      },
      {
        "metaRating": 49.416746078038415,
        "chemstyleId": 262,
        "playerRoleId": 18,
        "chemistry": 2,
        "isBestChemstyleAtChem": true
      },
      {
        "metaRating": 45.719099130175564,
        "chemstyleId": 268,
        "playerRoleId": 15,
        "chemistry": 2,
        "isBestChemstyleAtChem": true
      },
      {
        "metaRating": 42.263344441962815,
        "chemstyleId": 268,
        "playerRoleId": 19,
        "chemistry": 2,
        "isBestChemstyleAtChem": true
      },
      {
        "metaRating": 41.69242604113846,
        "chemstyleId": 268,
        "playerRoleId": 14,
        "chemistry": 2,
        "isBestChemstyleAtChem": true
      },
      {
        "metaRating": 37.845006545997805,
        "chemstyleId": 268,
        "playerRoleId": 17,
        "chemistry": 2,
        "isBestChemstyleAtChem": true
      },
      {
        "metaRating": 55.13330386297515,
        "chemstyleId": 260,
        "playerRoleId": 21,
        "chemistry": 3,
        "isBestChemstyleAtChem": true
      },
      {
        "metaRating": 54.41790838519734,
        "chemstyleId": 268,
        "playerRoleId": 16,
        "chemistry": 3,
        "isBestChemstyleAtChem": true
      },
      {
        "metaRating": 53.2776449886729,
        "chemstyleId": 268,
        "playerRoleId": 20,
        "chemistry": 3,
        "isBestChemstyleAtChem": true
      },
      {
        "metaRating": 52.02544619454644,
        "chemstyleId": 267,
        "playerRoleId": 22,
        "chemistry": 3,
        "isBestChemstyleAtChem": true
      },
      {
        "metaRating": 51.63519520475104,
        "chemstyleId": 268,
        "playerRoleId": 18,
        "chemistry": 3,
        "isBestChemstyleAtChem": true
      },
      {
        "metaRating": 48.806038621001626,
        "chemstyleId": 268,
        "playerRoleId": 15,
        "chemistry": 3,
        "isBestChemstyleAtChem": true
      },
      {
        "metaRating": 45.42346750404687,
        "chemstyleId": 268,
        "playerRoleId": 19,
        "chemistry": 3,
        "isBestChemstyleAtChem": true
      },
      {
        "metaRating": 44.90310517376809,
        "chemstyleId": 268,
        "playerRoleId": 14,
        "chemistry": 3,
        "isBestChemstyleAtChem": true
      },
      {
        "metaRating": 41.320778916910626,
        "chemstyleId": 268,
        "playerRoleId": 17,
        "chemistry": 3,
        "isBestChemstyleAtChem": true
      }
    ]
  },
  {
    "archetype": "deep_lying_playmaker",
    "ratings": [
      {
        "metaRating": 51.11003553026825,
        "chemstyleId": 250,
        "playerRoleId": 21,
        "chemistry": 0,
        "isBestChemstyleAtChem": true
      },
      {
        "metaRating": 49.66934120297338,
        "chemstyleId": 250,
        "playerRoleId": 16,
        "chemistry": 0,
        "isBestChemstyleAtChem": true
      },
      {
        "metaRating": 48.65603685465263,
        "chemstyleId": 250,
        "playerRoleId": 20,
        "chemistry": 0,
        "isBestChemstyleAtChem": true
      },
      {
        "metaRating": 47.45443692803328,
        "chemstyleId": 250,
        "playerRoleId": 22,
        "chemistry": 0,
        "isBestChemstyleAtChem": true
      },
      {
        "metaRating": 46.9165626504565,
        "chemstyleId": 250,
        "playerRoleId": 18,
        "chemistry": 0,
        "isBestChemstyleAtChem": true
      },
      {
        "metaRating": 42.535539433525976,
        "chemstyleId": 250,
        "playerRoleId": 15,
        "chemistry": 0,
        "isBestChemstyleAtChem": true
      },
      {
        "metaRating": 38.94279345318798,
        "chemstyleId": 250,
        "playerRoleId": 19,
        "chemistry": 0,
        "isBestChemstyleAtChem": true
      },
      {
        "metaRating": 38.3207234480641,
        "chemstyleId": 250,
        "playerRoleId": 14,
        "chemistry": 0,
        "isBestChemstyleAtChem": true
      },
      {
        "metaRating": 34.26378987183497,
        "chemstyleId": 250,
        "playerRoleId": 17,
        "chemistry": 0,
        "isBestChemstyleAtChem": true
      },
      {
        "metaRating": 52.12665880334177,
        "chemstyleId": 260,
        "playerRoleId": 21,
        "chemistry": 1,
        "isBestChemstyleAtChem": true
      },
      {
        "metaRating": 50.86740913743699,
        "chemstyleId": 268,
        "playerRoleId": 16,
        "chemistry": 1,
        "isBestChemstyleAtChem": true
      },
      {
        "metaRating": 49.82204752021474,
        "chemstyleId": 268,
        "playerRoleId": 20,
        "chemistry": 1,
        "isBestChemstyleAtChem": true
      },
      {
        "metaRating": 48.61132389243642,
        "chemstyleId": 267,
        "playerRoleId": 22,
        "chemistry": 1,
        "isBestChemstyleAtChem": true
      },
      {
        "metaRating": 48.10859888785463,
        "chemstyleId": 268,
        "playerRoleId": 18,
        "chemistry": 1,
        "isBestChemstyleAtChem": true
      },
      {
        "metaRating": 44.12073592370013,
        "chemstyleId": 268,
        "playerRoleId": 15,
        "chemistry": 1,
        "isBestChemstyleAtChem": true
      },
      {
        "metaRating": 40.5806841280159,
        "chemstyleId": 268,
        "playerRoleId": 19,
        "chemistry": 1,
        "isBestChemstyleAtChem": true
      },
      {
        "metaRating": 39.984223494336035,
        "chemstyleId": 268,
        "playerRoleId": 14,
        "chemistry": 1,
        "isBestChemstyleAtChem": true
      },
      {
        "metaRating": 36.047847942317425,
        "chemstyleId": 268,
        "playerRoleId": 17,
        "chemistry": 1,
        "isBestChemstyleAtChem": true
      },
      {
        "metaRating": 53.35392570023669,
        "chemstyleId": 262,
        "playerRoleId": 21,
        "chemistry": 2,
        "isBestChemstyleAtChem": true
      },
      {
        "metaRating": 52.37307527742976,
        "chemstyleId": 262,
        "playerRoleId": 16,
        "chemistry": 2,
        "isBestChemstyleAtChem": true
      },
      {
        "metaRating": 51.335058373085516,
        "chemstyleId": 262,
        "playerRoleId": 20,
        "chemistry": 2,
        "isBestChemstyleAtChem": true
      },
      {
        "metaRating": 49.81173204908924,
        "chemstyleId": 267,
        "playerRoleId": 22,
        "chemistry": 2,
        "isBestChemstyleAtChem": true
      },
      {
        "metaRating": 49.416746078038415,
        "chemstyleId": 262,
        "playerRoleId": 18,
        "chemistry": 2,
        "isBestChemstyleAtChem": true
      },
      {
        "metaRating": 45.719099130175564,
        "chemstyleId": 268,
        "playerRoleId": 15,
        "chemistry": 2,
        "isBestChemstyleAtChem": true
      },
      {
        "metaRating": 42.263344441962815,
        "chemstyleId": 268,
        "playerRoleId": 19,
        "chemistry": 2,
        "isBestChemstyleAtChem": true
      },
      {
        "metaRating": 41.69242604113846,
        "chemstyleId": 268,
        "playerRoleId": 14,
        "chemistry": 2,
        "isBestChemstyleAtChem": true
      },
      {
        "metaRating": 37.845006545997805,
        "chemstyleId": 268,
        "playerRoleId": 17,
        "chemistry": 2,
        "isBestChemstyleAtChem": true
      },
      {
        "metaRating": 55.13330386297515,
        "chemstyleId": 260,
        "playerRoleId": 21,
        "chemistry": 3,
        "isBestChemstyleAtChem": true
      },
      {
        "metaRating": 54.41790838519734,
        "chemstyleId": 268,
        "playerRoleId": 16,
        "chemistry": 3,
        "isBestChemstyleAtChem": true
      },
      {
        "metaRating": 53.2776449886729,
        "chemstyleId": 268,
        "playerRoleId": 20,
        "chemistry": 3,
        "isBestChemstyleAtChem": true
      },
      {
        "metaRating": 52.02544619454644,
        "chemstyleId": 267,
        "playerRoleId": 22,
        "chemistry": 3,
        "isBestChemstyleAtChem": true
      },
      {
        "metaRating": 51.63519520475104,
        "chemstyleId": 268,
        "playerRoleId": 18,
        "chemistry": 3,
        "isBestChemstyleAtChem": true
      },
      {
        "metaRating": 48.806038621001626,
        "chemstyleId": 268,
        "playerRoleId": 15,
        "chemistry": 3,
        "isBestChemstyleAtChem": true
      },
      {
        "metaRating": 45.42346750404687,
        "chemstyleId": 268,
        "playerRoleId": 19,
        "chemistry": 3,
        "isBestChemstyleAtChem": true
      },
      {
        "metaRating": 44.90310517376809,
        "chemstyleId": 268,
        "playerRoleId": 14,
        "chemistry": 3,
        "isBestChemstyleAtChem": true
      },
      {
        "metaRating": 41.320778916910626,
        "chemstyleId": 268,
        "playerRoleId": 17,
        "chemistry": 3,
        "isBestChemstyleAtChem": true
      }
    ]
  },
  {
    "archetype": "playmaker",
    "ratings": [
      {
        "metaRating": 51.11003553026825,
        "chemstyleId": 250,
        "playerRoleId": 21,
        "chemistry": 0,
        "isBestChemstyleAtChem": true
      },
      {
        "metaRating": 49.66934120297338,
        "chemstyleId": 250,
        "playerRoleId": 16,
        "chemistry": 0,
        "isBestChemstyleAtChem": true
      },
      {
        "metaRating": 48.65603685465263,
        "chemstyleId": 250,
        "playerRoleId": 20,
        "chemistry": 0,
        "isBestChemstyleAtChem": true
      },
      {
        "metaRating": 47.45443692803328,
        "chemstyleId": 250,
        "playerRoleId": 22,
        "chemistry": 0,
        "isBestChemstyleAtChem": true
      },
      {
        "metaRating": 46.9165626504565,
        "chemstyleId": 250,
        "playerRoleId": 18,
        "chemistry": 0,
        "isBestChemstyleAtChem": true
      },
      {
        "metaRating": 42.535539433525976,
        "chemstyleId": 250,
        "playerRoleId": 15,
        "chemistry": 0,
        "isBestChemstyleAtChem": true
      },
      {
        "metaRating": 38.94279345318798,
        "chemstyleId": 250,
        "playerRoleId": 19,
        "chemistry": 0,
        "isBestChemstyleAtChem": true
      },
      {
        "metaRating": 38.3207234480641,
        "chemstyleId": 250,
        "playerRoleId": 14,
        "chemistry": 0,
        "isBestChemstyleAtChem": true
      },
      {
        "metaRating": 34.26378987183497,
        "chemstyleId": 250,
        "playerRoleId": 17,
        "chemistry": 0,
        "isBestChemstyleAtChem": true
      },
      {
        "metaRating": 52.12665880334177,
        "chemstyleId": 260,
        "playerRoleId": 21,
        "chemistry": 1,
        "isBestChemstyleAtChem": true
      },
      {
        "metaRating": 50.86740913743699,
        "chemstyleId": 268,
        "playerRoleId": 16,
        "chemistry": 1,
        "isBestChemstyleAtChem": true
      },
      {
        "metaRating": 49.82204752021474,
        "chemstyleId": 268,
        "playerRoleId": 20,
        "chemistry": 1,
        "isBestChemstyleAtChem": true
      },
      {
        "metaRating": 48.61132389243642,
        "chemstyleId": 267,
        "playerRoleId": 22,
        "chemistry": 1,
        "isBestChemstyleAtChem": true
      },
      {
        "metaRating": 48.10859888785463,
        "chemstyleId": 268,
        "playerRoleId": 18,
        "chemistry": 1,
        "isBestChemstyleAtChem": true
      },
      {
        "metaRating": 44.12073592370013,
        "chemstyleId": 268,
        "playerRoleId": 15,
        "chemistry": 1,
        "isBestChemstyleAtChem": true
      },
      {
        "metaRating": 40.5806841280159,
        "chemstyleId": 268,
        "playerRoleId": 19,
        "chemistry": 1,
        "isBestChemstyleAtChem": true
      },
      {
        "metaRating": 39.984223494336035,
        "chemstyleId": 268,
        "playerRoleId": 14,
        "chemistry": 1,
        "isBestChemstyleAtChem": true
      },
      {
        "metaRating": 36.047847942317425,
        "chemstyleId": 268,
        "playerRoleId": 17,
        "chemistry": 1,
        "isBestChemstyleAtChem": true
      },
      {
        "metaRating": 53.35392570023669,
        "chemstyleId": 262,
        "playerRoleId": 21,
        "chemistry": 2,
        "isBestChemstyleAtChem": true
      },
      {
        "metaRating": 52.37307527742976,
        "chemstyleId": 262,
        "playerRoleId": 16,
        "chemistry": 2,
        "isBestChemstyleAtChem": true
      },
      {
        "metaRating": 51.335058373085516,
        "chemstyleId": 262,
        "playerRoleId": 20,
        "chemistry": 2,
        "isBestChemstyleAtChem": true
      },
      {
        "metaRating": 49.81173204908924,
        "chemstyleId": 267,
        "playerRoleId": 22,
        "chemistry": 2,
        "isBestChemstyleAtChem": true
      },
      {
        "metaRating": 49.416746078038415,
        "chemstyleId": 262,
        "playerRoleId": 18,
        "chemistry": 2,
        "isBestChemstyleAtChem": true
      },
      {
        "metaRating": 45.719099130175564,
        "chemstyleId": 268,
        "playerRoleId": 15,
        "chemistry": 2,
        "isBestChemstyleAtChem": true
      },
      {
        "metaRating": 42.263344441962815,
        "chemstyleId": 268,
        "playerRoleId": 19,
        "chemistry": 2,
        "isBestChemstyleAtChem": true
      },
      {
        "metaRating": 41.69242604113846,
        "chemstyleId": 268,
        "playerRoleId": 14,
        "chemistry": 2,
        "isBestChemstyleAtChem": true
      },
      {
        "metaRating": 37.845006545997805,
        "chemstyleId": 268,
        "playerRoleId": 17,
        "chemistry": 2,
        "isBestChemstyleAtChem": true
      },
      {
        "metaRating": 55.13330386297515,
        "chemstyleId": 260,
        "playerRoleId": 21,
        "chemistry": 3,
        "isBestChemstyleAtChem": true
      },
      {
        "metaRating": 54.41790838519734,
        "chemstyleId": 268,
        "playerRoleId": 16,
        "chemistry": 3,
        "isBestChemstyleAtChem": true
      },
      {
        "metaRating": 53.2776449886729,
        "chemstyleId": 268,
        "playerRoleId": 20,
        "chemistry": 3,
        "isBestChemstyleAtChem": true
      },
      {
        "metaRating": 52.02544619454644,
        "chemstyleId": 267,
        "playerRoleId": 22,
        "chemistry": 3,
        "isBestChemstyleAtChem": true
      },
      {
        "metaRating": 51.63519520475104,
        "chemstyleId": 268,
        "playerRoleId": 18,
        "chemistry": 3,
        "isBestChemstyleAtChem": true
      },
      {
        "metaRating": 48.806038621001626,
        "chemstyleId": 268,
        "playerRoleId": 15,
        "chemistry": 3,
        "isBestChemstyleAtChem": true
      },
      {
        "metaRating": 45.42346750404687,
        "chemstyleId": 268,
        "playerRoleId": 19,
        "chemistry": 3,
        "isBestChemstyleAtChem": true
      },
      {
        "metaRating": 44.90310517376809,
        "chemstyleId": 268,
        "playerRoleId": 14,
        "chemistry": 3,
        "isBestChemstyleAtChem": true
      },
      {
        "metaRating": 41.320778916910626,
        "chemstyleId": 268,
        "playerRoleId": 17,
        "chemistry": 3,
        "isBestChemstyleAtChem": true
      }
    ]
  },
  {
    "archetype": "half_winger",
    "ratings": [
      {
        "metaRating": 51.11003553026825,
        "chemstyleId": 250,
        "playerRoleId": 21,
        "chemistry": 0,
        "isBestChemstyleAtChem": true
      },
      {
        "metaRating": 49.66934120297338,
        "chemstyleId": 250,
        "playerRoleId": 16,
        "chemistry": 0,
        "isBestChemstyleAtChem": true
      },
      {
        "metaRating": 48.65603685465263,
        "chemstyleId": 250,
        "playerRoleId": 20,
        "chemistry": 0,
        "isBestChemstyleAtChem": true
      },
      {
        "metaRating": 47.45443692803328,
        "chemstyleId": 250,
        "playerRoleId": 22,
        "chemistry": 0,
        "isBestChemstyleAtChem": true
      },
      {
        "metaRating": 46.9165626504565,
        "chemstyleId": 250,
        "playerRoleId": 18,
        "chemistry": 0,
        "isBestChemstyleAtChem": true
      },
      {
        "metaRating": 42.535539433525976,
        "chemstyleId": 250,
        "playerRoleId": 15,
        "chemistry": 0,
        "isBestChemstyleAtChem": true
      },
      {
        "metaRating": 38.94279345318798,
        "chemstyleId": 250,
        "playerRoleId": 19,
        "chemistry": 0,
        "isBestChemstyleAtChem": true
      },
      {
        "metaRating": 38.3207234480641,
        "chemstyleId": 250,
        "playerRoleId": 14,
        "chemistry": 0,
        "isBestChemstyleAtChem": true
      },
      {
        "metaRating": 34.26378987183497,
        "chemstyleId": 250,
        "playerRoleId": 17,
        "chemistry": 0,
        "isBestChemstyleAtChem": true
      },
      {
        "metaRating": 52.12665880334177,
        "chemstyleId": 260,
        "playerRoleId": 21,
        "chemistry": 1,
        "isBestChemstyleAtChem": true
      },
      {
        "metaRating": 50.86740913743699,
        "chemstyleId": 268,
        "playerRoleId": 16,
        "chemistry": 1,
        "isBestChemstyleAtChem": true
      },
      {
        "metaRating": 49.82204752021474,
        "chemstyleId": 268,
        "playerRoleId": 20,
        "chemistry": 1,
        "isBestChemstyleAtChem": true
      },
      {
        "metaRating": 48.61132389243642,
        "chemstyleId": 267,
        "playerRoleId": 22,
        "chemistry": 1,
        "isBestChemstyleAtChem": true
      },
      {
        "metaRating": 48.10859888785463,
        "chemstyleId": 268,
        "playerRoleId": 18,
        "chemistry": 1,
        "isBestChemstyleAtChem": true
      },
      {
        "metaRating": 44.12073592370013,
        "chemstyleId": 268,
        "playerRoleId": 15,
        "chemistry": 1,
        "isBestChemstyleAtChem": true
      },
      {
        "metaRating": 40.5806841280159,
        "chemstyleId": 268,
        "playerRoleId": 19,
        "chemistry": 1,
        "isBestChemstyleAtChem": true
      },
      {
        "metaRating": 39.984223494336035,
        "chemstyleId": 268,
        "playerRoleId": 14,
        "chemistry": 1,
        "isBestChemstyleAtChem": true
      },
      {
        "metaRating": 36.047847942317425,
        "chemstyleId": 268,
        "playerRoleId": 17,
        "chemistry": 1,
        "isBestChemstyleAtChem": true
      },
      {
        "metaRating": 53.35392570023669,
        "chemstyleId": 262,
        "playerRoleId": 21,
        "chemistry": 2,
        "isBestChemstyleAtChem": true
      },
      {
        "metaRating": 52.37307527742976,
        "chemstyleId": 262,
        "playerRoleId": 16,
        "chemistry": 2,
        "isBestChemstyleAtChem": true
      },
      {
        "metaRating": 51.335058373085516,
        "chemstyleId": 262,
        "playerRoleId": 20,
        "chemistry": 2,
        "isBestChemstyleAtChem": true
      },
      {
        "metaRating": 49.81173204908924,
        "chemstyleId": 267,
        "playerRoleId": 22,
        "chemistry": 2,
        "isBestChemstyleAtChem": true
      },
      {
        "metaRating": 49.416746078038415,
        "chemstyleId": 262,
        "playerRoleId": 18,
        "chemistry": 2,
        "isBestChemstyleAtChem": true
      },
      {
        "metaRating": 45.719099130175564,
        "chemstyleId": 268,
        "playerRoleId": 15,
        "chemistry": 2,
        "isBestChemstyleAtChem": true
      },
      {
        "metaRating": 42.263344441962815,
        "chemstyleId": 268,
        "playerRoleId": 19,
        "chemistry": 2,
        "isBestChemstyleAtChem": true
      },
      {
        "metaRating": 41.69242604113846,
        "chemstyleId": 268,
        "playerRoleId": 14,
        "chemistry": 2,
        "isBestChemstyleAtChem": true
      },
      {
        "metaRating": 37.845006545997805,
        "chemstyleId": 268,
        "playerRoleId": 17,
        "chemistry": 2,
        "isBestChemstyleAtChem": true
      },
      {
        "metaRating": 55.13330386297515,
        "chemstyleId": 260,
        "playerRoleId": 21,
        "chemistry": 3,
        "isBestChemstyleAtChem": true
      },
      {
        "metaRating": 54.41790838519734,
        "chemstyleId": 268,
        "playerRoleId": 16,
        "chemistry": 3,
        "isBestChemstyleAtChem": true
      },
      {
        "metaRating": 53.2776449886729,
        "chemstyleId": 268,
        "playerRoleId": 20,
        "chemistry": 3,
        "isBestChemstyleAtChem": true
      },
      {
        "metaRating": 52.02544619454644,
        "chemstyleId": 267,
        "playerRoleId": 22,
        "chemistry": 3,
        "isBestChemstyleAtChem": true
      },
      {
        "metaRating": 51.63519520475104,
        "chemstyleId": 268,
        "playerRoleId": 18,
        "chemistry": 3,
        "isBestChemstyleAtChem": true
      },
      {
        "metaRating": 48.806038621001626,
        "chemstyleId": 268,
        "playerRoleId": 15,
        "chemistry": 3,
        "isBestChemstyleAtChem": true
      },
      {
        "metaRating": 45.42346750404687,
        "chemstyleId": 268,
        "playerRoleId": 19,
        "chemistry": 3,
        "isBestChemstyleAtChem": true
      },
      {
        "metaRating": 44.90310517376809,
        "chemstyleId": 268,
        "playerRoleId": 14,
        "chemistry": 3,
        "isBestChemstyleAtChem": true
      },
      {
        "metaRating": 41.320778916910626,
        "chemstyleId": 268,
        "playerRoleId": 17,
        "chemistry": 3,
        "isBestChemstyleAtChem": true
      }
    ]
  },
  {
    "archetype": "box_to_box",
    "ratings": [
      {
        "metaRating": 51.11003553026825,
        "chemstyleId": 250,
        "playerRoleId": 21,
        "chemistry": 0,
        "isBestChemstyleAtChem": true
      },
      {
        "metaRating": 49.66934120297338,
        "chemstyleId": 250,
        "playerRoleId": 16,
        "chemistry": 0,
        "isBestChemstyleAtChem": true
      },
      {
        "metaRating": 48.65603685465263,
        "chemstyleId": 250,
        "playerRoleId": 20,
        "chemistry": 0,
        "isBestChemstyleAtChem": true
      },
      {
        "metaRating": 47.45443692803328,
        "chemstyleId": 250,
        "playerRoleId": 22,
        "chemistry": 0,
        "isBestChemstyleAtChem": true
      },
      {
        "metaRating": 46.9165626504565,
        "chemstyleId": 250,
        "playerRoleId": 18,
        "chemistry": 0,
        "isBestChemstyleAtChem": true
      },
      {
        "metaRating": 42.535539433525976,
        "chemstyleId": 250,
        "playerRoleId": 15,
        "chemistry": 0,
        "isBestChemstyleAtChem": true
      },
      {
        "metaRating": 38.94279345318798,
        "chemstyleId": 250,
        "playerRoleId": 19,
        "chemistry": 0,
        "isBestChemstyleAtChem": true
      },
      {
        "metaRating": 38.3207234480641,
        "chemstyleId": 250,
        "playerRoleId": 14,
        "chemistry": 0,
        "isBestChemstyleAtChem": true
      },
      {
        "metaRating": 34.26378987183497,
        "chemstyleId": 250,
        "playerRoleId": 17,
        "chemistry": 0,
        "isBestChemstyleAtChem": true
      },
      {
        "metaRating": 52.12665880334177,
        "chemstyleId": 260,
        "playerRoleId": 21,
        "chemistry": 1,
        "isBestChemstyleAtChem": true
      },
      {
        "metaRating": 50.86740913743699,
        "chemstyleId": 268,
        "playerRoleId": 16,
        "chemistry": 1,
        "isBestChemstyleAtChem": true
      },
      {
        "metaRating": 49.82204752021474,
        "chemstyleId": 268,
        "playerRoleId": 20,
        "chemistry": 1,
        "isBestChemstyleAtChem": true
      },
      {
        "metaRating": 48.61132389243642,
        "chemstyleId": 267,
        "playerRoleId": 22,
        "chemistry": 1,
        "isBestChemstyleAtChem": true
      },
      {
        "metaRating": 48.10859888785463,
        "chemstyleId": 268,
        "playerRoleId": 18,
        "chemistry": 1,
        "isBestChemstyleAtChem": true
      },
      {
        "metaRating": 44.12073592370013,
        "chemstyleId": 268,
        "playerRoleId": 15,
        "chemistry": 1,
        "isBestChemstyleAtChem": true
      },
      {
        "metaRating": 40.5806841280159,
        "chemstyleId": 268,
        "playerRoleId": 19,
        "chemistry": 1,
        "isBestChemstyleAtChem": true
      },
      {
        "metaRating": 39.984223494336035,
        "chemstyleId": 268,
        "playerRoleId": 14,
        "chemistry": 1,
        "isBestChemstyleAtChem": true
      },
      {
        "metaRating": 36.047847942317425,
        "chemstyleId": 268,
        "playerRoleId": 17,
        "chemistry": 1,
        "isBestChemstyleAtChem": true
      },
      {
        "metaRating": 53.35392570023669,
        "chemstyleId": 262,
        "playerRoleId": 21,
        "chemistry": 2,
        "isBestChemstyleAtChem": true
      },
      {
        "metaRating": 52.37307527742976,
        "chemstyleId": 262,
        "playerRoleId": 16,
        "chemistry": 2,
        "isBestChemstyleAtChem": true
      },
      {
        "metaRating": 51.335058373085516,
        "chemstyleId": 262,
        "playerRoleId": 20,
        "chemistry": 2,
        "isBestChemstyleAtChem": true
      },
      {
        "metaRating": 49.81173204908924,
        "chemstyleId": 267,
        "playerRoleId": 22,
        "chemistry": 2,
        "isBestChemstyleAtChem": true
      },
      {
        "metaRating": 49.416746078038415,
        "chemstyleId": 262,
        "playerRoleId": 18,
        "chemistry": 2,
        "isBestChemstyleAtChem": true
      },
      {
        "metaRating": 45.719099130175564,
        "chemstyleId": 268,
        "playerRoleId": 15,
        "chemistry": 2,
        "isBestChemstyleAtChem": true
      },
      {
        "metaRating": 42.263344441962815,
        "chemstyleId": 268,
        "playerRoleId": 19,
        "chemistry": 2,
        "isBestChemstyleAtChem": true
      },
      {
        "metaRating": 41.69242604113846,
        "chemstyleId": 268,
        "playerRoleId": 14,
        "chemistry": 2,
        "isBestChemstyleAtChem": true
      },
      {
        "metaRating": 37.845006545997805,
        "chemstyleId": 268,
        "playerRoleId": 17,
        "chemistry": 2,
        "isBestChemstyleAtChem": true
      },
      {
        "metaRating": 55.13330386297515,
        "chemstyleId": 260,
        "playerRoleId": 21,
        "chemistry": 3,
        "isBestChemstyleAtChem": true
      },
      {
        "metaRating": 54.41790838519734,
        "chemstyleId": 268,
        "playerRoleId": 16,
        "chemistry": 3,
        "isBestChemstyleAtChem": true
      },
      {
        "metaRating": 53.2776449886729,
        "chemstyleId": 268,
        "playerRoleId": 20,
        "chemistry": 3,
        "isBestChemstyleAtChem": true
      },
      {
        "metaRating": 52.02544619454644,
        "chemstyleId": 267,
        "playerRoleId": 22,
        "chemistry": 3,
        "isBestChemstyleAtChem": true
      },
      {
        "metaRating": 51.63519520475104,
        "chemstyleId": 268,
        "playerRoleId": 18,
        "chemistry": 3,
        "isBestChemstyleAtChem": true
      },
      {
        "metaRating": 48.806038621001626,
        "chemstyleId": 268,
        "playerRoleId": 15,
        "chemistry": 3,
        "isBestChemstyleAtChem": true
      },
      {
        "metaRating": 45.42346750404687,
        "chemstyleId": 268,
        "playerRoleId": 19,
        "chemistry": 3,
        "isBestChemstyleAtChem": true
      },
      {
        "metaRating": 44.90310517376809,
        "chemstyleId": 268,
        "playerRoleId": 14,
        "chemistry": 3,
        "isBestChemstyleAtChem": true
      },
      {
        "metaRating": 41.320778916910626,
        "chemstyleId": 268,
        "playerRoleId": 17,
        "chemistry": 3,
        "isBestChemstyleAtChem": true
      }
    ]
  },
  {
    "archetype": "wide_half",
    "ratings": [
      {
        "metaRating": 51.11003553026825,
        "chemstyleId": 250,
        "playerRoleId": 21,
        "chemistry": 0,
        "isBestChemstyleAtChem": true
      },
      {
        "metaRating": 49.66934120297338,
        "chemstyleId": 250,
        "playerRoleId": 16,
        "chemistry": 0,
        "isBestChemstyleAtChem": true
      },
      {
        "metaRating": 48.65603685465263,
        "chemstyleId": 250,
        "playerRoleId": 20,
        "chemistry": 0,
        "isBestChemstyleAtChem": true
      },
      {
        "metaRating": 47.45443692803328,
        "chemstyleId": 250,
        "playerRoleId": 22,
        "chemistry": 0,
        "isBestChemstyleAtChem": true
      },
      {
        "metaRating": 46.9165626504565,
        "chemstyleId": 250,
        "playerRoleId": 18,
        "chemistry": 0,
        "isBestChemstyleAtChem": true
      },
      {
        "metaRating": 42.535539433525976,
        "chemstyleId": 250,
        "playerRoleId": 15,
        "chemistry": 0,
        "isBestChemstyleAtChem": true
      },
      {
        "metaRating": 38.94279345318798,
        "chemstyleId": 250,
        "playerRoleId": 19,
        "chemistry": 0,
        "isBestChemstyleAtChem": true
      },
      {
        "metaRating": 38.3207234480641,
        "chemstyleId": 250,
        "playerRoleId": 14,
        "chemistry": 0,
        "isBestChemstyleAtChem": true
      },
      {
        "metaRating": 34.26378987183497,
        "chemstyleId": 250,
        "playerRoleId": 17,
        "chemistry": 0,
        "isBestChemstyleAtChem": true
      },
      {
        "metaRating": 52.12665880334177,
        "chemstyleId": 260,
        "playerRoleId": 21,
        "chemistry": 1,
        "isBestChemstyleAtChem": true
      },
      {
        "metaRating": 50.86740913743699,
        "chemstyleId": 268,
        "playerRoleId": 16,
        "chemistry": 1,
        "isBestChemstyleAtChem": true
      },
      {
        "metaRating": 49.82204752021474,
        "chemstyleId": 268,
        "playerRoleId": 20,
        "chemistry": 1,
        "isBestChemstyleAtChem": true
      },
      {
        "metaRating": 48.61132389243642,
        "chemstyleId": 267,
        "playerRoleId": 22,
        "chemistry": 1,
        "isBestChemstyleAtChem": true
      },
      {
        "metaRating": 48.10859888785463,
        "chemstyleId": 268,
        "playerRoleId": 18,
        "chemistry": 1,
        "isBestChemstyleAtChem": true
      },
      {
        "metaRating": 44.12073592370013,
        "chemstyleId": 268,
        "playerRoleId": 15,
        "chemistry": 1,
        "isBestChemstyleAtChem": true
      },
      {
        "metaRating": 40.5806841280159,
        "chemstyleId": 268,
        "playerRoleId": 19,
        "chemistry": 1,
        "isBestChemstyleAtChem": true
      },
      {
        "metaRating": 39.984223494336035,
        "chemstyleId": 268,
        "playerRoleId": 14,
        "chemistry": 1,
        "isBestChemstyleAtChem": true
      },
      {
        "metaRating": 36.047847942317425,
        "chemstyleId": 268,
        "playerRoleId": 17,
        "chemistry": 1,
        "isBestChemstyleAtChem": true
      },
      {
        "metaRating": 53.35392570023669,
        "chemstyleId": 262,
        "playerRoleId": 21,
        "chemistry": 2,
        "isBestChemstyleAtChem": true
      },
      {
        "metaRating": 52.37307527742976,
        "chemstyleId": 262,
        "playerRoleId": 16,
        "chemistry": 2,
        "isBestChemstyleAtChem": true
      },
      {
        "metaRating": 51.335058373085516,
        "chemstyleId": 262,
        "playerRoleId": 20,
        "chemistry": 2,
        "isBestChemstyleAtChem": true
      },
      {
        "metaRating": 49.81173204908924,
        "chemstyleId": 267,
        "playerRoleId": 22,
        "chemistry": 2,
        "isBestChemstyleAtChem": true
      },
      {
        "metaRating": 49.416746078038415,
        "chemstyleId": 262,
        "playerRoleId": 18,
        "chemistry": 2,
        "isBestChemstyleAtChem": true
      },
      {
        "metaRating": 45.719099130175564,
        "chemstyleId": 268,
        "playerRoleId": 15,
        "chemistry": 2,
        "isBestChemstyleAtChem": true
      },
      {
        "metaRating": 42.263344441962815,
        "chemstyleId": 268,
        "playerRoleId": 19,
        "chemistry": 2,
        "isBestChemstyleAtChem": true
      },
      {
        "metaRating": 41.69242604113846,
        "chemstyleId": 268,
        "playerRoleId": 14,
        "chemistry": 2,
        "isBestChemstyleAtChem": true
      },
      {
        "metaRating": 37.845006545997805,
        "chemstyleId": 268,
        "playerRoleId": 17,
        "chemistry": 2,
        "isBestChemstyleAtChem": true
      },
      {
        "metaRating": 55.13330386297515,
        "chemstyleId": 260,
        "playerRoleId": 21,
        "chemistry": 3,
        "isBestChemstyleAtChem": true
      },
      {
        "metaRating": 54.41790838519734,
        "chemstyleId": 268,
        "playerRoleId": 16,
        "chemistry": 3,
        "isBestChemstyleAtChem": true
      },
      {
        "metaRating": 53.2776449886729,
        "chemstyleId": 268,
        "playerRoleId": 20,
        "chemistry": 3,
        "isBestChemstyleAtChem": true
      },
      {
        "metaRating": 52.02544619454644,
        "chemstyleId": 267,
        "playerRoleId": 22,
        "chemistry": 3,
        "isBestChemstyleAtChem": true
      },
      {
        "metaRating": 51.63519520475104,
        "chemstyleId": 268,
        "playerRoleId": 18,
        "chemistry": 3,
        "isBestChemstyleAtChem": true
      },
      {
        "metaRating": 48.806038621001626,
        "chemstyleId": 268,
        "playerRoleId": 15,
        "chemistry": 3,
        "isBestChemstyleAtChem": true
      },
      {
        "metaRating": 45.42346750404687,
        "chemstyleId": 268,
        "playerRoleId": 19,
        "chemistry": 3,
        "isBestChemstyleAtChem": true
      },
      {
        "metaRating": 44.90310517376809,
        "chemstyleId": 268,
        "playerRoleId": 14,
        "chemistry": 3,
        "isBestChemstyleAtChem": true
      },
      {
        "metaRating": 41.320778916910626,
        "chemstyleId": 268,
        "playerRoleId": 17,
        "chemistry": 3,
        "isBestChemstyleAtChem": true
      }
    ]
  },
  {
    "archetype": "centre_half",
    "ratings": [
      {
        "metaRating": 51.11003553026825,
        "chemstyleId": 250,
        "playerRoleId": 21,
        "chemistry": 0,
        "isBestChemstyleAtChem": true
      },
      {
        "metaRating": 49.66934120297338,
        "chemstyleId": 250,
        "playerRoleId": 16,
        "chemistry": 0,
        "isBestChemstyleAtChem": true
      },
      {
        "metaRating": 48.65603685465263,
        "chemstyleId": 250,
        "playerRoleId": 20,
        "chemistry": 0,
        "isBestChemstyleAtChem": true
      },
      {
        "metaRating": 47.45443692803328,
        "chemstyleId": 250,
        "playerRoleId": 22,
        "chemistry": 0,
        "isBestChemstyleAtChem": true
      },
      {
        "metaRating": 46.9165626504565,
        "chemstyleId": 250,
        "playerRoleId": 18,
        "chemistry": 0,
        "isBestChemstyleAtChem": true
      },
      {
        "metaRating": 42.535539433525976,
        "chemstyleId": 250,
        "playerRoleId": 15,
        "chemistry": 0,
        "isBestChemstyleAtChem": true
      },
      {
        "metaRating": 38.94279345318798,
        "chemstyleId": 250,
        "playerRoleId": 19,
        "chemistry": 0,
        "isBestChemstyleAtChem": true
      },
      {
        "metaRating": 38.3207234480641,
        "chemstyleId": 250,
        "playerRoleId": 14,
        "chemistry": 0,
        "isBestChemstyleAtChem": true
      },
      {
        "metaRating": 34.26378987183497,
        "chemstyleId": 250,
        "playerRoleId": 17,
        "chemistry": 0,
        "isBestChemstyleAtChem": true
      },
      {
        "metaRating": 52.12665880334177,
        "chemstyleId": 260,
        "playerRoleId": 21,
        "chemistry": 1,
        "isBestChemstyleAtChem": true
      },
      {
        "metaRating": 50.86740913743699,
        "chemstyleId": 268,
        "playerRoleId": 16,
        "chemistry": 1,
        "isBestChemstyleAtChem": true
      },
      {
        "metaRating": 49.82204752021474,
        "chemstyleId": 268,
        "playerRoleId": 20,
        "chemistry": 1,
        "isBestChemstyleAtChem": true
      },
      {
        "metaRating": 48.61132389243642,
        "chemstyleId": 267,
        "playerRoleId": 22,
        "chemistry": 1,
        "isBestChemstyleAtChem": true
      },
      {
        "metaRating": 48.10859888785463,
        "chemstyleId": 268,
        "playerRoleId": 18,
        "chemistry": 1,
        "isBestChemstyleAtChem": true
      },
      {
        "metaRating": 44.12073592370013,
        "chemstyleId": 268,
        "playerRoleId": 15,
        "chemistry": 1,
        "isBestChemstyleAtChem": true
      },
      {
        "metaRating": 40.5806841280159,
        "chemstyleId": 268,
        "playerRoleId": 19,
        "chemistry": 1,
        "isBestChemstyleAtChem": true
      },
      {
        "metaRating": 39.984223494336035,
        "chemstyleId": 268,
        "playerRoleId": 14,
        "chemistry": 1,
        "isBestChemstyleAtChem": true
      },
      {
        "metaRating": 36.047847942317425,
        "chemstyleId": 268,
        "playerRoleId": 17,
        "chemistry": 1,
        "isBestChemstyleAtChem": true
      },
      {
        "metaRating": 53.35392570023669,
        "chemstyleId": 262,
        "playerRoleId": 21,
        "chemistry": 2,
        "isBestChemstyleAtChem": true
      },
      {
        "metaRating": 52.37307527742976,
        "chemstyleId": 262,
        "playerRoleId": 16,
        "chemistry": 2,
        "isBestChemstyleAtChem": true
      },
      {
        "metaRating": 51.335058373085516,
        "chemstyleId": 262,
        "playerRoleId": 20,
        "chemistry": 2,
        "isBestChemstyleAtChem": true
      },
      {
        "metaRating": 49.81173204908924,
        "chemstyleId": 267,
        "playerRoleId": 22,
        "chemistry": 2,
        "isBestChemstyleAtChem": true
      },
      {
        "metaRating": 49.416746078038415,
        "chemstyleId": 262,
        "playerRoleId": 18,
        "chemistry": 2,
        "isBestChemstyleAtChem": true
      },
      {
        "metaRating": 45.719099130175564,
        "chemstyleId": 268,
        "playerRoleId": 15,
        "chemistry": 2,
        "isBestChemstyleAtChem": true
      },
      {
        "metaRating": 42.263344441962815,
        "chemstyleId": 268,
        "playerRoleId": 19,
        "chemistry": 2,
        "isBestChemstyleAtChem": true
      },
      {
        "metaRating": 41.69242604113846,
        "chemstyleId": 268,
        "playerRoleId": 14,
        "chemistry": 2,
        "isBestChemstyleAtChem": true
      },
      {
        "metaRating": 37.845006545997805,
        "chemstyleId": 268,
        "playerRoleId": 17,
        "chemistry": 2,
        "isBestChemstyleAtChem": true
      },
      {
        "metaRating": 55.13330386297515,
        "chemstyleId": 260,
        "playerRoleId": 21,
        "chemistry": 3,
        "isBestChemstyleAtChem": true
      },
      {
        "metaRating": 54.41790838519734,
        "chemstyleId": 268,
        "playerRoleId": 16,
        "chemistry": 3,
        "isBestChemstyleAtChem": true
      },
      {
        "metaRating": 53.2776449886729,
        "chemstyleId": 268,
        "playerRoleId": 20,
        "chemistry": 3,
        "isBestChemstyleAtChem": true
      },
      {
        "metaRating": 52.02544619454644,
        "chemstyleId": 267,
        "playerRoleId": 22,
        "chemistry": 3,
        "isBestChemstyleAtChem": true
      },
      {
        "metaRating": 51.63519520475104,
        "chemstyleId": 268,
        "playerRoleId": 18,
        "chemistry": 3,
        "isBestChemstyleAtChem": true
      },
      {
        "metaRating": 48.806038621001626,
        "chemstyleId": 268,
        "playerRoleId": 15,
        "chemistry": 3,
        "isBestChemstyleAtChem": true
      },
      {
        "metaRating": 45.42346750404687,
        "chemstyleId": 268,
        "playerRoleId": 19,
        "chemistry": 3,
        "isBestChemstyleAtChem": true
      },
      {
        "metaRating": 44.90310517376809,
        "chemstyleId": 268,
        "playerRoleId": 14,
        "chemistry": 3,
        "isBestChemstyleAtChem": true
      },
      {
        "metaRating": 41.320778916910626,
        "chemstyleId": 268,
        "playerRoleId": 17,
        "chemistry": 3,
        "isBestChemstyleAtChem": true
      }
    ]
  }
]