[
  {
    "archetype": "ball_playing_defender",
    "ratings": [
      {
        "metaRating": 66.19667123417354,
        "chemstyleId": 250,
        "archetypeId": "ball_playing_defender",
        "chemistry": 0,
        "isBestChemstyleAtChem": true
      },
      {
        "metaRating": 67.41887072715527,
        "chemstyleId": 268,
        "archetypeId": "ball_playing_defender",
        "chemistry": 1,
        "isBestChemstyleAtChem": true
      },
      {
        "metaRating": 68.68222897426237,
        "chemstyleId": 268,
        "archetypeId": "ball_playing_defender",
        "chemistry": 2,
        "isBestChemstyleAtChem": true
      },
      {
        "metaRating": 70.92480028142327,
        "chemstyleId": 268,
        "archetypeId": "ball_playing_defender",
        "chemistry": 3,
        "isBestChemstyleAtChem": true
      }
    ]
  },
  {
    "archetype": "defender",
    "ratings": [
      {
        "metaRating": 71.1899783869159,
        "chemstyleId": 250,
        "archetypeId": "defender",
        "chemistry": 0,
        "isBestChemstyleAtChem": true
      },
      {
        "metaRating": 72.90497050369326,
        "chemstyleId": 268,
        "archetypeId": "defender",
        "chemistry": 1,
        "isBestChemstyleAtChem": true
      },
      {
        "metaRating": 74.70067595824571,
        "chemstyleId": 268,
        "archetypeId": "defender",
        "chemistry": 2,
        "isBestChemstyleAtChem": true
      },
      {
        "metaRating": 77.81891676018157,
        "chemstyleId": 268,
        "archetypeId": "defender",
        "chemistry": 3,
        "isBestChemstyleAtChem": true
      }
    ]
  },
  {
    "archetype": "stopper",
    "ratings": [
      {
        "metaRating": 64.12087110233989,
        "chemstyleId": 250,
        "archetypeId": "stopper",
        "chemistry": 0,
        "isBestChemstyleAtChem": true
      },
      {
        "metaRating": 65.83361783613812,
        "chemstyleId": 268,
        "archetypeId": "stopper",
        "chemistry": 1,
        "isBestChemstyleAtChem": true
      },
      {
        "metaRating": 67.655198177366,
        "chemstyleId": 268,
        "archetypeId": "stopper",
        "chemistry": 2,
        "isBestChemstyleAtChem": true
      },
      {
        "metaRating": 70.76446027308971,
        "chemstyleId": 268,
        "archetypeId": "stopper",
        "chemistry": 3,
        "isBestChemstyleAtChem": true
      }
    ]
  }
]