[
  {
    "archetype": "holding",
    "ratings": [
      {
        "metaRating": 63.643049521783276,
        "chemstyleId": 250,
        "playerRoleId": 14,
        "chemistry": 0,
        "isBestChemstyleAtChem": true
      },
      {
        "metaRating": 62.88684147241679,
        "chemstyleId": 250,
        "playerRoleId": 20,
        "chemistry": 0,
        "isBestChemstyleAtChem": true
      },
      {
        "metaRating": 62.86721194153033,
        "chemstyleId": 250,
        "playerRoleId": 21,
        "chemistry": 0,
        "isBestChemstyleAtChem": true
      },
      {
        "metaRating": 62.78127594426742,
        "chemstyleId": 250,
        "playerRoleId": 18,
        "chemistry": 0,
        "isBestChemstyleAtChem": true
      },
      {
        "metaRating": 62.49536128884936,
        "chemstyleId": 250,
        "playerRoleId": 16,
        "chemistry": 0,
        "isBestChemstyleAtChem": true
      },
      {
        "metaRating": 62.09454799030262,
        "chemstyleId": 250,
        "playerRoleId": 19,
        "chemistry": 0,
        "isBestChemstyleAtChem": true
      },
      {
        "metaRating": 60.801704175636765,
        "chemstyleId": 250,
        "playerRoleId": 22,
        "chemistry": 0,
        "isBestChemstyleAtChem": true
      },
      {
        "metaRating": 59.536515019726494,
        "chemstyleId": 250,
        "playerRoleId": 15,
        "chemistry": 0,
        "isBestChemstyleAtChem": true
      },
      {
        "metaRating": 58.16144303809609,
        "chemstyleId": 250,
        "playerRoleId": 17,
        "chemistry": 0,
        "isBestChemstyleAtChem": true
      },
      {
        "metaRating": 65.10402325058136,
        "chemstyleId": 268,
        "playerRoleId": 14,
        "chemistry": 1,
        "isBestChemstyleAtChem": true
      },
      {
        "metaRating": 63.98750422776932,
        "chemstyleId": 262,
        "playerRoleId": 20,
        "chemistry": 1,
        "isBestChemstyleAtChem": true
      },
      {
        "metaRating": 63.82933416076488,
        "chemstyleId": 268,
        "playerRoleId": 18,
        "chemistry": 1,
        "isBestChemstyleAtChem": true
      },
      {
        "metaRating": 63.818290520709056,
        "chemstyleId": 260,
        "playerRoleId": 21,
        "chemistry": 1,
        "isBestChemstyleAtChem": true
      },
      {
        "metaRating": 63.60757406779273,
        "chemstyleId": 262,
        "playerRoleId": 16,
        "chemistry": 1,
        "isBestChemstyleAtChem": true
      },
      {
        "metaRating": 63.53355590911327,
        "chemstyleId": 268,
        "playerRoleId": 19,
        "chemistry": 1,
        "isBestChemstyleAtChem": true
      },
      {
        "metaRating": 61.81998373961114,
        "chemstyleId": 267,
        "playerRoleId": 22,
        "chemistry": 1,
        "isBestChemstyleAtChem": true
      },
      {
        "metaRating": 60.91635600258931,
        "chemstyleId": 268,
        "playerRoleId": 15,
        "chemistry": 1,
        "isBestChemstyleAtChem": true
      },
      {
        "metaRating": 59.72175990918032,
        "chemstyleId": 268,
        "playerRoleId": 17,
        "chemistry": 1,
        "isBestChemstyleAtChem": true
      },
      {
        "metaRating": 66.59875078702746,
        "chemstyleId": 268,
        "playerRoleId": 14,
        "chemistry": 2,
        "isBestChemstyleAtChem": true
      },
      {
        "metaRating": 65.41989412015327,
        "chemstyleId": 262,
        "playerRoleId": 20,
        "chemistry": 2,
        "isBestChemstyleAtChem": true
      },
      {
        "metaRating": 65.14026887214541,
        "chemstyleId": 262,
        "playerRoleId": 18,
        "chemistry": 2,
        "isBestChemstyleAtChem": true
      },
      {
        "metaRating": 65.05979064730651,
        "chemstyleId": 262,
        "playerRoleId": 21,
        "chemistry": 2,
        "isBestChemstyleAtChem": true
      },
      {
        "metaRating": 65.049785773903,
        "chemstyleId": 262,
        "playerRoleId": 16,
        "chemistry": 2,
        "isBestChemstyleAtChem": true
      },
      {
        "metaRating": 65.0064909746856,
        "chemstyleId": 268,
        "playerRoleId": 19,
        "chemistry": 2,
        "isBestChemstyleAtChem": true
      },
      {
        "metaRating": 62.873885150247325,
        "chemstyleId": 267,
        "playerRoleId": 22,
        "chemistry": 2,
        "isBestChemstyleAtChem": true
      },
      {
        "metaRating": 62.2981491397117,
        "chemstyleId": 268,
        "playerRoleId": 15,
        "chemistry": 2,
        "isBestChemstyleAtChem": true
      },
      {
        "metaRating": 61.283080966300645,
        "chemstyleId": 268,
        "playerRoleId": 17,
        "chemistry": 2,
        "isBestChemstyleAtChem": true
      },
      {
        "metaRating": 69.34280830891744,
        "chemstyleId": 268,
        "playerRoleId": 14,
        "chemistry": 3,
        "isBestChemstyleAtChem": true
      },
      {
        "metaRating": 67.70784400072135,
        "chemstyleId": 268,
        "playerRoleId": 19,
        "chemistry": 3,
        "isBestChemstyleAtChem": true
      },
      {
        "metaRating": 67.1941097742313,
        "chemstyleId": 262,
        "playerRoleId": 20,
        "chemistry": 3,
        "isBestChemstyleAtChem": true
      },
      {
        "metaRating": 66.87058714991676,
        "chemstyleId": 268,
        "playerRoleId": 18,
        "chemistry": 3,
        "isBestChemstyleAtChem": true
      },
      {
        "metaRating": 66.84856357181,
        "chemstyleId": 262,
        "playerRoleId": 16,
        "chemistry": 3,
        "isBestChemstyleAtChem": true
      },
      {
        "metaRating": 66.61126091413989,
        "chemstyleId": 260,
        "playerRoleId": 21,
        "chemistry": 3,
        "isBestChemstyleAtChem": true
      },
      {
        "metaRating": 64.91122854232084,
        "chemstyleId": 268,
        "playerRoleId": 15,
        "chemistry": 3,
        "isBestChemstyleAtChem": true
      },
      {
        "metaRating": 64.76587684962524,
        "chemstyleId": 267,
        "playerRoleId": 22,
        "chemistry": 3,
        "isBestChemstyleAtChem": true
      },
      {
        "metaRating": 64.24332290613451,
        "chemstyleId": 268,
        "playerRoleId": 17,
        "chemistry": 3,
        "isBestChemstyleAtChem": true
      }
    ]
  },
  {
    "archetype": "deep_lying_playmaker",
    "ratings": [
      {
        "metaRating": 63.643049521783276,
        "chemstyleId": 250,
        "playerRoleId": 14,
        "chemistry": 0,
        "isBestChemstyleAtChem": true
      },
      {
        "metaRating": 62.88684147241679,
        "chemstyleId": 250,
        "playerRoleId": 20,
        "chemistry": 0,
        "isBestChemstyleAtChem": true
      },
      {
        "metaRating": 62.86721194153033,
        "chemstyleId": 250,
        "playerRoleId": 21,
        "chemistry": 0,
        "isBestChemstyleAtChem": true
      },
      {
        "metaRating": 62.78127594426742,
        "chemstyleId": 250,
        "playerRoleId": 18,
        "chemistry": 0,
        "isBestChemstyleAtChem": true
      },
      {
        "metaRating": 62.49536128884936,
        "chemstyleId": 250,
        "playerRoleId": 16,
        "chemistry": 0,
        "isBestChemstyleAtChem": true
      },
      {
        "metaRating": 62.09454799030262,
        "chemstyleId": 250,
        "playerRoleId": 19,
        "chemistry": 0,
        "isBestChemstyleAtChem": true
      },
      {
        "metaRating": 60.801704175636765,
        "chemstyleId": 250,
        "playerRoleId": 22,
        "chemistry": 0,
        "isBestChemstyleAtChem": true
      },
      {
        "metaRating": 59.536515019726494,
        "chemstyleId": 250,
        "playerRoleId": 15,
        "chemistry": 0,
        "isBestChemstyleAtChem": true
      },
      {
        "metaRating": 58.16144303809609,
        "chemstyleId": 250,
        "playerRoleId": 17,
        "chemistry": 0,
        "isBestChemstyleAtChem": true
      },
      {
        "metaRating": 65.10402325058136,
        "chemstyleId": 268,
        "playerRoleId": 14,
        "chemistry": 1,
        "isBestChemstyleAtChem": true
      },
      {
        "metaRating": 63.98750422776932,
        "chemstyleId": 262,
        "playerRoleId": 20,
        "chemistry": 1,
        "isBestChemstyleAtChem": true
      },
      {
        "metaRating": 63.82933416076488,
        "chemstyleId": 268,
        "playerRoleId": 18,
        "chemistry": 1,
        "isBestChemstyleAtChem": true
      },
      {
        "metaRating": 63.818290520709056,
        "chemstyleId": 260,
        "playerRoleId": 21,
        "chemistry": 1,
        "isBestChemstyleAtChem": true
      },
      {
        "metaRating": 63.60757406779273,
        "chemstyleId": 262,
        "playerRoleId": 16,
        "chemistry": 1,
        "isBestChemstyleAtChem": true
      },
      {
        "metaRating": 63.53355590911327,
        "chemstyleId": 268,
        "playerRoleId": 19,
        "chemistry": 1,
        "isBestChemstyleAtChem": true
      },
      {
        "metaRating": 61.81998373961114,
        "chemstyleId": 267,
        "playerRoleId": 22,
        "chemistry": 1,
        "isBestChemstyleAtChem": true
      },
      {
        "metaRating": 60.91635600258931,
        "chemstyleId": 268,
        "playerRoleId": 15,
        "chemistry": 1,
        "isBestChemstyleAtChem": true
      },
      {
        "metaRating": 59.72175990918032,
        "chemstyleId": 268,
        "playerRoleId": 17,
        "chemistry": 1,
        "isBestChemstyleAtChem": true
      },
      {
        "metaRating": 66.59875078702746,
        "chemstyleId": 268,
        "playerRoleId": 14,
        "chemistry": 2,
        "isBestChemstyleAtChem": true
      },
      {
        "metaRating": 65.41989412015327,
        "chemstyleId": 262,
        "playerRoleId": 20,
        "chemistry": 2,
        "isBestChemstyleAtChem": true
      },
      {
        "metaRating": 65.14026887214541,
        "chemstyleId": 262,
        "playerRoleId": 18,
        "chemistry": 2,
        "isBestChemstyleAtChem": true
      },
      {
        "metaRating": 65.05979064730651,
        "chemstyleId": 262,
        "playerRoleId": 21,
        "chemistry": 2,
        "isBestChemstyleAtChem": true
      },
      {
        "metaRating": 65.049785773903,
        "chemstyleId": 262,
        "playerRoleId": 16,
        "chemistry": 2,
        "isBestChemstyleAtChem": true
      },
      {
        "metaRating": 65.0064909746856,
        "chemstyleId": 268,
        "playerRoleId": 19,
        "chemistry": 2,
        "isBestChemstyleAtChem": true
      },
      {
        "metaRating": 62.873885150247325,
        "chemstyleId": 267,
        "playerRoleId": 22,
        "chemistry": 2,
        "isBestChemstyleAtChem": true
      },
      {
        "metaRating": 62.2981491397117,
        "chemstyleId": 268,
        "playerRoleId": 15,
        "chemistry": 2,
        "isBestChemstyleAtChem": true
      },
      {
        "metaRating": 61.283080966300645,
        "chemstyleId": 268,
        "playerRoleId": 17,
        "chemistry": 2,
        "isBestChemstyleAtChem": true
      },
      {
        "metaRating": 69.34280830891744,
        "chemstyleId": 268,
        "playerRoleId": 14,
        "chemistry": 3,
        "isBestChemstyleAtChem": true
      },
      {
        "metaRating": 67.70784400072135,
        "chemstyleId": 268,
        "playerRoleId": 19,
        "chemistry": 3,
        "isBestChemstyleAtChem": true
      },
      {
        "metaRating": 67.1941097742313,
        "chemstyleId": 262,
        "playerRoleId": 20,
        "chemistry": 3,
        "isBestChemstyleAtChem": true
      },
      {
        "metaRating": 66.87058714991676,
        "chemstyleId": 268,
        "playerRoleId": 18,
        "chemistry": 3,
        "isBestChemstyleAtChem": true
      },
      {
        "metaRating": 66.84856357181,
        "chemstyleId": 262,
        "playerRoleId": 16,
        "chemistry": 3,
        "isBestChemstyleAtChem": true
      },
      {
        "metaRating": 66.61126091413989,
        "chemstyleId": 260,
        "playerRoleId": 21,
        "chemistry": 3,
        "isBestChemstyleAtChem": true
      },
      {
        "metaRating": 64.91122854232084,
        "chemstyleId": 268,
        "playerRoleId": 15,
        "chemistry": 3,
        "isBestChemstyleAtChem": true
      },
      {
        "metaRating": 64.76587684962524,
        "chemstyleId": 267,
        "playerRoleId": 22,
        "chemistry": 3,
        "isBestChemstyleAtChem": true
      },
      {
        "metaRating": 64.24332290613451,
        "chemstyleId": 268,
        "playerRoleId": 17,
        "chemistry": 3,
        "isBestChemstyleAtChem": true
      }
    ]
  },
  {
    "archetype": "wide_half",
    "ratings": [
      {
        "metaRating": 63.643049521783276,
        "chemstyleId": 250,
        "playerRoleId": 14,
        "chemistry": 0,
        "isBestChemstyleAtChem": true
      },
      {
        "metaRating": 62.88684147241679,
        "chemstyleId": 250,
        "playerRoleId": 20,
        "chemistry": 0,
        "isBestChemstyleAtChem": true
      },
      {
        "metaRating": 62.86721194153033,
        "chemstyleId": 250,
        "playerRoleId": 21,
        "chemistry": 0,
        "isBestChemstyleAtChem": true
      },
      {
        "metaRating": 62.78127594426742,
        "chemstyleId": 250,
        "playerRoleId": 18,
        "chemistry": 0,
        "isBestChemstyleAtChem": true
      },
      {
        "metaRating": 62.49536128884936,
        "chemstyleId": 250,
        "playerRoleId": 16,
        "chemistry": 0,
        "isBestChemstyleAtChem": true
      },
      {
        "metaRating": 62.09454799030262,
        "chemstyleId": 250,
        "playerRoleId": 19,
        "chemistry": 0,
        "isBestChemstyleAtChem": true
      },
      {
        "metaRating": 60.801704175636765,
        "chemstyleId": 250,
        "playerRoleId": 22,
        "chemistry": 0,
        "isBestChemstyleAtChem": true
      },
      {
        "metaRating": 59.536515019726494,
        "chemstyleId": 250,
        "playerRoleId": 15,
        "chemistry": 0,
        "isBestChemstyleAtChem": true
      },
      {
        "metaRating": 58.16144303809609,
        "chemstyleId": 250,
        "playerRoleId": 17,
        "chemistry": 0,
        "isBestChemstyleAtChem": true
      },
      {
        "metaRating": 65.10402325058136,
        "chemstyleId": 268,
        "playerRoleId": 14,
        "chemistry": 1,
        "isBestChemstyleAtChem": true
      },
      {
        "metaRating": 63.98750422776932,
        "chemstyleId": 262,
        "playerRoleId": 20,
        "chemistry": 1,
        "isBestChemstyleAtChem": true
      },
      {
        "metaRating": 63.82933416076488,
        "chemstyleId": 268,
        "playerRoleId": 18,
        "chemistry": 1,
        "isBestChemstyleAtChem": true
      },
      {
        "metaRating": 63.818290520709056,
        "chemstyleId": 260,
        "playerRoleId": 21,
        "chemistry": 1,
        "isBestChemstyleAtChem": true
      },
      {
        "metaRating": 63.60757406779273,
        "chemstyleId": 262,
        "playerRoleId": 16,
        "chemistry": 1,
        "isBestChemstyleAtChem": true
      },
      {
        "metaRating": 63.53355590911327,
        "chemstyleId": 268,
        "playerRoleId": 19,
        "chemistry": 1,
        "isBestChemstyleAtChem": true
      },
      {
        "metaRating": 61.81998373961114,
        "chemstyleId": 267,
        "playerRoleId": 22,
        "chemistry": 1,
        "isBestChemstyleAtChem": true
      },
      {
        "metaRating": 60.91635600258931,
        "chemstyleId": 268,
        "playerRoleId": 15,
        "chemistry": 1,
        "isBestChemstyleAtChem": true
      },
      {
        "metaRating": 59.72175990918032,
        "chemstyleId": 268,
        "playerRoleId": 17,
        "chemistry": 1,
        "isBestChemstyleAtChem": true
      },
      {
        "metaRating": 66.59875078702746,
        "chemstyleId": 268,
        "playerRoleId": 14,
        "chemistry": 2,
        "isBestChemstyleAtChem": true
      },
      {
        "metaRating": 65.41989412015327,
        "chemstyleId": 262,
        "playerRoleId": 20,
        "chemistry": 2,
        "isBestChemstyleAtChem": true
      },
      {
        "metaRating": 65.14026887214541,
        "chemstyleId": 262,
        "playerRoleId": 18,
        "chemistry": 2,
        "isBestChemstyleAtChem": true
      },
      {
        "metaRating": 65.05979064730651,
        "chemstyleId": 262,
        "playerRoleId": 21,
        "chemistry": 2,
        "isBestChemstyleAtChem": true
      },
      {
        "metaRating": 65.049785773903,
        "chemstyleId": 262,
        "playerRoleId": 16,
        "chemistry": 2,
        "isBestChemstyleAtChem": true
      },
      {
        "metaRating": 65.0064909746856,
        "chemstyleId": 268,
        "playerRoleId": 19,
        "chemistry": 2,
        "isBestChemstyleAtChem": true
      },
      {
        "metaRating": 62.873885150247325,
        "chemstyleId": 267,
        "playerRoleId": 22,
        "chemistry": 2,
        "isBestChemstyleAtChem": true
      },
      {
        "metaRating": 62.2981491397117,
        "chemstyleId": 268,
        "playerRoleId": 15,
        "chemistry": 2,
        "isBestChemstyleAtChem": true
      },
      {
        "metaRating": 61.283080966300645,
        "chemstyleId": 268,
        "playerRoleId": 17,
        "chemistry": 2,
        "isBestChemstyleAtChem": true
      },
      {
        "metaRating": 69.34280830891744,
        "chemstyleId": 268,
        "playerRoleId": 14,
        "chemistry": 3,
        "isBestChemstyleAtChem": true
      },
      {
        "metaRating": 67.70784400072135,
        "chemstyleId": 268,
        "playerRoleId": 19,
        "chemistry": 3,
        "isBestChemstyleAtChem": true
      },
      {
        "metaRating": 67.1941097742313,
        "chemstyleId": 262,
        "playerRoleId": 20,
        "chemistry": 3,
        "isBestChemstyleAtChem": true
      },
      {
        "metaRating": 66.87058714991676,
        "chemstyleId": 268,
        "playerRoleId": 18,
        "chemistry": 3,
        "isBestChemstyleAtChem": true
      },
      {
        "metaRating": 66.84856357181,
        "chemstyleId": 262,
        "playerRoleId": 16,
        "chemistry": 3,
        "isBestChemstyleAtChem": true
      },
      {
        "metaRating": 66.61126091413989,
        "chemstyleId": 260,
        "playerRoleId": 21,
        "chemistry": 3,
        "isBestChemstyleAtChem": true
      },
      {
        "metaRating": 64.91122854232084,
        "chemstyleId": 268,
        "playerRoleId": 15,
        "chemistry": 3,
        "isBestChemstyleAtChem": true
      },
      {
        "metaRating": 64.76587684962524,
        "chemstyleId": 267,
        "playerRoleId": 22,
        "chemistry": 3,
        "isBestChemstyleAtChem": true
      },
      {
        "metaRating": 64.24332290613451,
        "chemstyleId": 268,
        "playerRoleId": 17,
        "chemistry": 3,
        "isBestChemstyleAtChem": true
      }
    ]
  },
  {
    "archetype": "centre_half",
    "ratings": [
      {
        "metaRating": 63.643049521783276,
        "chemstyleId": 250,
        "playerRoleId": 14,
        "chemistry": 0,
        "isBestChemstyleAtChem": true
      },
      {
        "metaRating": 62.88684147241679,
        "chemstyleId": 250,
        "playerRoleId": 20,
        "chemistry": 0,
        "isBestChemstyleAtChem": true
      },
      {
        "metaRating": 62.86721194153033,
        "chemstyleId": 250,
        "playerRoleId": 21,
        "chemistry": 0,
        "isBestChemstyleAtChem": true
      },
      {
        "metaRating": 62.78127594426742,
        "chemstyleId": 250,
        "playerRoleId": 18,
        "chemistry": 0,
        "isBestChemstyleAtChem": true
      },
      {
        "metaRating": 62.49536128884936,
        "chemstyleId": 250,
        "playerRoleId": 16,
        "chemistry": 0,
        "isBestChemstyleAtChem": true
      },
      {
        "metaRating": 62.09454799030262,
        "chemstyleId": 250,
        "playerRoleId": 19,
        "chemistry": 0,
        "isBestChemstyleAtChem": true
      },
      {
        "metaRating": 60.801704175636765,
        "chemstyleId": 250,
        "playerRoleId": 22,
        "chemistry": 0,
        "isBestChemstyleAtChem": true
      },
      {
        "metaRating": 59.536515019726494,
        "chemstyleId": 250,
        "playerRoleId": 15,
        "chemistry": 0,
        "isBestChemstyleAtChem": true
      },
      {
        "metaRating": 58.16144303809609,
        "chemstyleId": 250,
        "playerRoleId": 17,
        "chemistry": 0,
        "isBestChemstyleAtChem": true
      },
      {
        "metaRating": 65.10402325058136,
        "chemstyleId": 268,
        "playerRoleId": 14,
        "chemistry": 1,
        "isBestChemstyleAtChem": true
      },
      {
        "metaRating": 63.98750422776932,
        "chemstyleId": 262,
        "playerRoleId": 20,
        "chemistry": 1,
        "isBestChemstyleAtChem": true
      },
      {
        "metaRating": 63.82933416076488,
        "chemstyleId": 268,
        "playerRoleId": 18,
        "chemistry": 1,
        "isBestChemstyleAtChem": true
      },
      {
        "metaRating": 63.818290520709056,
        "chemstyleId": 260,
        "playerRoleId": 21,
        "chemistry": 1,
        "isBestChemstyleAtChem": true
      },
      {
        "metaRating": 63.60757406779273,
        "chemstyleId": 262,
        "playerRoleId": 16,
        "chemistry": 1,
        "isBestChemstyleAtChem": true
      },
      {
        "metaRating": 63.53355590911327,
        "chemstyleId": 268,
        "playerRoleId": 19,
        "chemistry": 1,
        "isBestChemstyleAtChem": true
      },
      {
        "metaRating": 61.81998373961114,
        "chemstyleId": 267,
        "playerRoleId": 22,
        "chemistry": 1,
        "isBestChemstyleAtChem": true
      },
      {
        "metaRating": 60.91635600258931,
        "chemstyleId": 268,
        "playerRoleId": 15,
        "chemistry": 1,
        "isBestChemstyleAtChem": true
      },
      {
        "metaRating": 59.72175990918032,
        "chemstyleId": 268,
        "playerRoleId": 17,
        "chemistry": 1,
        "isBestChemstyleAtChem": true
      },
      {
        "metaRating": 66.59875078702746,
        "chemstyleId": 268,
        "playerRoleId": 14,
        "chemistry": 2,
        "isBestChemstyleAtChem": true
      },
      {
        "metaRating": 65.41989412015327,
        "chemstyleId": 262,
        "playerRoleId": 20,
        "chemistry": 2,
        "isBestChemstyleAtChem": true
      },
      {
        "metaRating": 65.14026887214541,
        "chemstyleId": 262,
        "playerRoleId": 18,
        "chemistry": 2,
        "isBestChemstyleAtChem": true
      },
      {
        "metaRating": 65.05979064730651,
        "chemstyleId": 262,
        "playerRoleId": 21,
        "chemistry": 2,
        "isBestChemstyleAtChem": true
      },
      {
        "metaRating": 65.049785773903,
        "chemstyleId": 262,
        "playerRoleId": 16,
        "chemistry": 2,
        "isBestChemstyleAtChem": true
      },
      {
        "metaRating": 65.0064909746856,
        "chemstyleId": 268,
        "playerRoleId": 19,
        "chemistry": 2,
        "isBestChemstyleAtChem": true
      },
      {
        "metaRating": 62.873885150247325,
        "chemstyleId": 267,
        "playerRoleId": 22,
        "chemistry": 2,
        "isBestChemstyleAtChem": true
      },
      {
        "metaRating": 62.2981491397117,
        "chemstyleId": 268,
        "playerRoleId": 15,
        "chemistry": 2,
        "isBestChemstyleAtChem": true
      },
      {
        "metaRating": 61.283080966300645,
        "chemstyleId": 268,
        "playerRoleId": 17,
        "chemistry": 2,
        "isBestChemstyleAtChem": true
      },
      {
        "metaRating": 69.34280830891744,
        "chemstyleId": 268,
        "playerRoleId": 14,
        "chemistry": 3,
        "isBestChemstyleAtChem": true
      },
      {
        "metaRating": 67.70784400072135,
        "chemstyleId": 268,
        "playerRoleId": 19,
        "chemistry": 3,
        "isBestChemstyleAtChem": true
      },
      {
        "metaRating": 67.1941097742313,
        "chemstyleId": 262,
        "playerRoleId": 20,
        "chemistry": 3,
        "isBestChemstyleAtChem": true
      },
      {
        "metaRating": 66.87058714991676,
        "chemstyleId": 268,
        "playerRoleId": 18,
        "chemistry": 3,
        "isBestChemstyleAtChem": true
      },
      {
        "metaRating": 66.84856357181,
        "chemstyleId": 262,
        "playerRoleId": 16,
        "chemistry": 3,
        "isBestChemstyleAtChem": true
      },
      {
        "metaRating": 66.61126091413989,
        "chemstyleId": 260,
        "playerRoleId": 21,
        "chemistry": 3,
        "isBestChemstyleAtChem": true
      },
      {
        "metaRating": 64.91122854232084,
        "chemstyleId": 268,
        "playerRoleId": 15,
        "chemistry": 3,
        "isBestChemstyleAtChem": true
      },
      {
        "metaRating": 64.76587684962524,
        "chemstyleId": 267,
        "playerRoleId": 22,
        "chemistry": 3,
        "isBestChemstyleAtChem": true
      },
      {
        "metaRating": 64.24332290613451,
        "chemstyleId": 268,
        "playerRoleId": 17,
        "chemistry": 3,
        "isBestChemstyleAtChem": true
      }
    ]
  },
  {
    "archetype": "playmaker",
    "ratings": [
      {
        "metaRating": 63.643049521783276,
        "chemstyleId": 250,
        "playerRoleId": 14,
        "chemistry": 0,
        "isBestChemstyleAtChem": true
      },
      {
        "metaRating": 62.88684147241679,
        "chemstyleId": 250,
        "playerRoleId": 20,
        "chemistry": 0,
        "isBestChemstyleAtChem": true
      },
      {
        "metaRating": 62.86721194153033,
        "chemstyleId": 250,
        "playerRoleId": 21,
        "chemistry": 0,
        "isBestChemstyleAtChem": true
      },
      {
        "metaRating": 62.78127594426742,
        "chemstyleId": 250,
        "playerRoleId": 18,
        "chemistry": 0,
        "isBestChemstyleAtChem": true
      },
      {
        "metaRating": 62.49536128884936,
        "chemstyleId": 250,
        "playerRoleId": 16,
        "chemistry": 0,
        "isBestChemstyleAtChem": true
      },
      {
        "metaRating": 62.09454799030262,
        "chemstyleId": 250,
        "playerRoleId": 19,
        "chemistry": 0,
        "isBestChemstyleAtChem": true
      },
      {
        "metaRating": 60.801704175636765,
        "chemstyleId": 250,
        "playerRoleId": 22,
        "chemistry": 0,
        "isBestChemstyleAtChem": true
      },
      {
        "metaRating": 59.536515019726494,
        "chemstyleId": 250,
        "playerRoleId": 15,
        "chemistry": 0,
        "isBestChemstyleAtChem": true
      },
      {
        "metaRating": 58.16144303809609,
        "chemstyleId": 250,
        "playerRoleId": 17,
        "chemistry": 0,
        "isBestChemstyleAtChem": true
      },
      {
        "metaRating": 65.10402325058136,
        "chemstyleId": 268,
        "playerRoleId": 14,
        "chemistry": 1,
        "isBestChemstyleAtChem": true
      },
      {
        "metaRating": 63.98750422776932,
        "chemstyleId": 262,
        "playerRoleId": 20,
        "chemistry": 1,
        "isBestChemstyleAtChem": true
      },
      {
        "metaRating": 63.82933416076488,
        "chemstyleId": 268,
        "playerRoleId": 18,
        "chemistry": 1,
        "isBestChemstyleAtChem": true
      },
      {
        "metaRating": 63.818290520709056,
        "chemstyleId": 260,
        "playerRoleId": 21,
        "chemistry": 1,
        "isBestChemstyleAtChem": true
      },
      {
        "metaRating": 63.60757406779273,
        "chemstyleId": 262,
        "playerRoleId": 16,
        "chemistry": 1,
        "isBestChemstyleAtChem": true
      },
      {
        "metaRating": 63.53355590911327,
        "chemstyleId": 268,
        "playerRoleId": 19,
        "chemistry": 1,
        "isBestChemstyleAtChem": true
      },
      {
        "metaRating": 61.81998373961114,
        "chemstyleId": 267,
        "playerRoleId": 22,
        "chemistry": 1,
        "isBestChemstyleAtChem": true
      },
      {
        "metaRating": 60.91635600258931,
        "chemstyleId": 268,
        "playerRoleId": 15,
        "chemistry": 1,
        "isBestChemstyleAtChem": true
      },
      {
        "metaRating": 59.72175990918032,
        "chemstyleId": 268,
        "playerRoleId": 17,
        "chemistry": 1,
        "isBestChemstyleAtChem": true
      },
      {
        "metaRating": 66.59875078702746,
        "chemstyleId": 268,
        "playerRoleId": 14,
        "chemistry": 2,
        "isBestChemstyleAtChem": true
      },
      {
        "metaRating": 65.41989412015327,
        "chemstyleId": 262,
        "playerRoleId": 20,
        "chemistry": 2,
        "isBestChemstyleAtChem": true
      },
      {
        "metaRating": 65.14026887214541,
        "chemstyleId": 262,
        "playerRoleId": 18,
        "chemistry": 2,
        "isBestChemstyleAtChem": true
      },
      {
        "metaRating": 65.05979064730651,
        "chemstyleId": 262,
        "playerRoleId": 21,
        "chemistry": 2,
        "isBestChemstyleAtChem": true
      },
      {
        "metaRating": 65.049785773903,
        "chemstyleId": 262,
        "playerRoleId": 16,
        "chemistry": 2,
        "isBestChemstyleAtChem": true
      },
      {
        "metaRating": 65.0064909746856,
        "chemstyleId": 268,
        "playerRoleId": 19,
        "chemistry": 2,
        "isBestChemstyleAtChem": true
      },
      {
        "metaRating": 62.873885150247325,
        "chemstyleId": 267,
        "playerRoleId": 22,
        "chemistry": 2,
        "isBestChemstyleAtChem": true
      },
      {
        "metaRating": 62.2981491397117,
        "chemstyleId": 268,
        "playerRoleId": 15,
        "chemistry": 2,
        "isBestChemstyleAtChem": true
      },
      {
        "metaRating": 61.283080966300645,
        "chemstyleId": 268,
        "playerRoleId": 17,
        "chemistry": 2,
        "isBestChemstyleAtChem": true
      },
      {
        "metaRating": 69.34280830891744,
        "chemstyleId": 268,
        "playerRoleId": 14,
        "chemistry": 3,
        "isBestChemstyleAtChem": true
      },
      {
        "metaRating": 67.70784400072135,
        "chemstyleId": 268,
        "playerRoleId": 19,
        "chemistry": 3,
        "isBestChemstyleAtChem": true
      },
      {
        "metaRating": 67.1941097742313,
        "chemstyleId": 262,
        "playerRoleId": 20,
        "chemistry": 3,
        "isBestChemstyleAtChem": true
      },
      {
        "metaRating": 66.87058714991676,
        "chemstyleId": 268,
        "playerRoleId": 18,
        "chemistry": 3,
        "isBestChemstyleAtChem": true
      },
      {
        "metaRating": 66.84856357181,
        "chemstyleId": 262,
        "playerRoleId": 16,
        "chemistry": 3,
        "isBestChemstyleAtChem": true
      },
      {
        "metaRating": 66.61126091413989,
        "chemstyleId": 260,
        "playerRoleId": 21,
        "chemistry": 3,
        "isBestChemstyleAtChem": true
      },
      {
        "metaRating": 64.91122854232084,
        "chemstyleId": 268,
        "playerRoleId": 15,
        "chemistry": 3,
        "isBestChemstyleAtChem": true
      },
      {
        "metaRating": 64.76587684962524,
        "chemstyleId": 267,
        "playerRoleId": 22,
        "chemistry": 3,
        "isBestChemstyleAtChem": true
      },
      {
        "metaRating": 64.24332290613451,
        "chemstyleId": 268,
        "playerRoleId": 17,
        "chemistry": 3,
        "isBestChemstyleAtChem": true
      }
    ]
  },
  {
    "archetype": "half_winger",
    "ratings": [
      {
        "metaRating": 63.643049521783276,
        "chemstyleId": 250,
        "playerRoleId": 14,
        "chemistry": 0,
        "isBestChemstyleAtChem": true
      },
      {
        "metaRating": 62.88684147241679,
        "chemstyleId": 250,
        "playerRoleId": 20,
        "chemistry": 0,
        "isBestChemstyleAtChem": true
      },
      {
        "metaRating": 62.86721194153033,
        "chemstyleId": 250,
        "playerRoleId": 21,
        "chemistry": 0,
        "isBestChemstyleAtChem": true
      },
      {
        "metaRating": 62.78127594426742,
        "chemstyleId": 250,
        "playerRoleId": 18,
        "chemistry": 0,
        "isBestChemstyleAtChem": true
      },
      {
        "metaRating": 62.49536128884936,
        "chemstyleId": 250,
        "playerRoleId": 16,
        "chemistry": 0,
        "isBestChemstyleAtChem": true
      },
      {
        "metaRating": 62.09454799030262,
        "chemstyleId": 250,
        "playerRoleId": 19,
        "chemistry": 0,
        "isBestChemstyleAtChem": true
      },
      {
        "metaRating": 60.801704175636765,
        "chemstyleId": 250,
        "playerRoleId": 22,
        "chemistry": 0,
        "isBestChemstyleAtChem": true
      },
      {
        "metaRating": 59.536515019726494,
        "chemstyleId": 250,
        "playerRoleId": 15,
        "chemistry": 0,
        "isBestChemstyleAtChem": true
      },
      {
        "metaRating": 58.16144303809609,
        "chemstyleId": 250,
        "playerRoleId": 17,
        "chemistry": 0,
        "isBestChemstyleAtChem": true
      },
      {
        "metaRating": 65.10402325058136,
        "chemstyleId": 268,
        "playerRoleId": 14,
        "chemistry": 1,
        "isBestChemstyleAtChem": true
      },
      {
        "metaRating": 63.98750422776932,
        "chemstyleId": 262,
        "playerRoleId": 20,
        "chemistry": 1,
        "isBestChemstyleAtChem": true
      },
      {
        "metaRating": 63.82933416076488,
        "chemstyleId": 268,
        "playerRoleId": 18,
        "chemistry": 1,
        "isBestChemstyleAtChem": true
      },
      {
        "metaRating": 63.818290520709056,
        "chemstyleId": 260,
        "playerRoleId": 21,
        "chemistry": 1,
        "isBestChemstyleAtChem": true
      },
      {
        "metaRating": 63.60757406779273,
        "chemstyleId": 262,
        "playerRoleId": 16,
        "chemistry": 1,
        "isBestChemstyleAtChem": true
      },
      {
        "metaRating": 63.53355590911327,
        "chemstyleId": 268,
        "playerRoleId": 19,
        "chemistry": 1,
        "isBestChemstyleAtChem": true
      },
      {
        "metaRating": 61.81998373961114,
        "chemstyleId": 267,
        "playerRoleId": 22,
        "chemistry": 1,
        "isBestChemstyleAtChem": true
      },
      {
        "metaRating": 60.91635600258931,
        "chemstyleId": 268,
        "playerRoleId": 15,
        "chemistry": 1,
        "isBestChemstyleAtChem": true
      },
      {
        "metaRating": 59.72175990918032,
        "chemstyleId": 268,
        "playerRoleId": 17,
        "chemistry": 1,
        "isBestChemstyleAtChem": true
      },
      {
        "metaRating": 66.59875078702746,
        "chemstyleId": 268,
        "playerRoleId": 14,
        "chemistry": 2,
        "isBestChemstyleAtChem": true
      },
      {
        "metaRating": 65.41989412015327,
        "chemstyleId": 262,
        "playerRoleId": 20,
        "chemistry": 2,
        "isBestChemstyleAtChem": true
      },
      {
        "metaRating": 65.14026887214541,
        "chemstyleId": 262,
        "playerRoleId": 18,
        "chemistry": 2,
        "isBestChemstyleAtChem": true
      },
      {
        "metaRating": 65.05979064730651,
        "chemstyleId": 262,
        "playerRoleId": 21,
        "chemistry": 2,
        "isBestChemstyleAtChem": true
      },
      {
        "metaRating": 65.049785773903,
        "chemstyleId": 262,
        "playerRoleId": 16,
        "chemistry": 2,
        "isBestChemstyleAtChem": true
      },
      {
        "metaRating": 65.0064909746856,
        "chemstyleId": 268,
        "playerRoleId": 19,
        "chemistry": 2,
        "isBestChemstyleAtChem": true
      },
      {
        "metaRating": 62.873885150247325,
        "chemstyleId": 267,
        "playerRoleId": 22,
        "chemistry": 2,
        "isBestChemstyleAtChem": true
      },
      {
        "metaRating": 62.2981491397117,
        "chemstyleId": 268,
        "playerRoleId": 15,
        "chemistry": 2,
        "isBestChemstyleAtChem": true
      },
      {
        "metaRating": 61.283080966300645,
        "chemstyleId": 268,
        "playerRoleId": 17,
        "chemistry": 2,
        "isBestChemstyleAtChem": true
      },
      {
        "metaRating": 69.34280830891744,
        "chemstyleId": 268,
        "playerRoleId": 14,
        "chemistry": 3,
        "isBestChemstyleAtChem": true
      },
      {
        "metaRating": 67.70784400072135,
        "chemstyleId": 268,
        "playerRoleId": 19,
        "chemistry": 3,
        "isBestChemstyleAtChem": true
      },
      {
        "metaRating": 67.1941097742313,
        "chemstyleId": 262,
        "playerRoleId": 20,
        "chemistry": 3,
        "isBestChemstyleAtChem": true
      },
      {
        "metaRating": 66.87058714991676,
        "chemstyleId": 268,
        "playerRoleId": 18,
        "chemistry": 3,
        "isBestChemstyleAtChem": true
      },
      {
        "metaRating": 66.84856357181,
        "chemstyleId": 262,
        "playerRoleId": 16,
        "chemistry": 3,
        "isBestChemstyleAtChem": true
      },
      {
        "metaRating": 66.61126091413989,
        "chemstyleId": 260,
        "playerRoleId": 21,
        "chemistry": 3,
        "isBestChemstyleAtChem": true
      },
      {
        "metaRating": 64.91122854232084,
        "chemstyleId": 268,
        "playerRoleId": 15,
        "chemistry": 3,
        "isBestChemstyleAtChem": true
      },
      {
        "metaRating": 64.76587684962524,
        "chemstyleId": 267,
        "playerRoleId": 22,
        "chemistry": 3,
        "isBestChemstyleAtChem": true
      },
      {
        "metaRating": 64.24332290613451,
        "chemstyleId": 268,
        "playerRoleId": 17,
        "chemistry": 3,
        "isBestChemstyleAtChem": true
      }
    ]
  },
  {
    "archetype": "box_to_box",
    "ratings": [
      {
        "metaRating": 63.643049521783276,
        "chemstyleId": 250,
        "playerRoleId": 14,
        "chemistry": 0,
        "isBestChemstyleAtChem": true
      },
      {
        "metaRating": 62.88684147241679,
        "chemstyleId": 250,
        "playerRoleId": 20,
        "chemistry": 0,
        "isBestChemstyleAtChem": true
      },
      {
        "metaRating": 62.86721194153033,
        "chemstyleId": 250,
        "playerRoleId": 21,
        "chemistry": 0,
        "isBestChemstyleAtChem": true
      },
      {
        "metaRating": 62.78127594426742,
        "chemstyleId": 250,
        "playerRoleId": 18,
        "chemistry": 0,
        "isBestChemstyleAtChem": true
      },
      {
        "metaRating": 62.49536128884936,
        "chemstyleId": 250,
        "playerRoleId": 16,
        "chemistry": 0,
        "isBestChemstyleAtChem": true
      },
      {
        "metaRating": 62.09454799030262,
        "chemstyleId": 250,
        "playerRoleId": 19,
        "chemistry": 0,
        "isBestChemstyleAtChem": true
      },
      {
        "metaRating": 60.801704175636765,
        "chemstyleId": 250,
        "playerRoleId": 22,
        "chemistry": 0,
        "isBestChemstyleAtChem": true
      },
      {
        "metaRating": 59.536515019726494,
        "chemstyleId": 250,
        "playerRoleId": 15,
        "chemistry": 0,
        "isBestChemstyleAtChem": true
      },
      {
        "metaRating": 58.16144303809609,
        "chemstyleId": 250,
        "playerRoleId": 17,
        "chemistry": 0,
        "isBestChemstyleAtChem": true
      },
      {
        "metaRating": 65.10402325058136,
        "chemstyleId": 268,
        "playerRoleId": 14,
        "chemistry": 1,
        "isBestChemstyleAtChem": true
      },
      {
        "metaRating": 63.98750422776932,
        "chemstyleId": 262,
        "playerRoleId": 20,
        "chemistry": 1,
        "isBestChemstyleAtChem": true
      },
      {
        "metaRating": 63.82933416076488,
        "chemstyleId": 268,
        "playerRoleId": 18,
        "chemistry": 1,
        "isBestChemstyleAtChem": true
      },
      {
        "metaRating": 63.818290520709056,
        "chemstyleId": 260,
        "playerRoleId": 21,
        "chemistry": 1,
        "isBestChemstyleAtChem": true
      },
      {
        "metaRating": 63.60757406779273,
        "chemstyleId": 262,
        "playerRoleId": 16,
        "chemistry": 1,
        "isBestChemstyleAtChem": true
      },
      {
        "metaRating": 63.53355590911327,
        "chemstyleId": 268,
        "playerRoleId": 19,
        "chemistry": 1,
        "isBestChemstyleAtChem": true
      },
      {
        "metaRating": 61.81998373961114,
        "chemstyleId": 267,
        "playerRoleId": 22,
        "chemistry": 1,
        "isBestChemstyleAtChem": true
      },
      {
        "metaRating": 60.91635600258931,
        "chemstyleId": 268,
        "playerRoleId": 15,
        "chemistry": 1,
        "isBestChemstyleAtChem": true
      },
      {
        "metaRating": 59.72175990918032,
        "chemstyleId": 268,
        "playerRoleId": 17,
        "chemistry": 1,
        "isBestChemstyleAtChem": true
      },
      {
        "metaRating": 66.59875078702746,
        "chemstyleId": 268,
        "playerRoleId": 14,
        "chemistry": 2,
        "isBestChemstyleAtChem": true
      },
      {
        "metaRating": 65.41989412015327,
        "chemstyleId": 262,
        "playerRoleId": 20,
        "chemistry": 2,
        "isBestChemstyleAtChem": true
      },
      {
        "metaRating": 65.14026887214541,
        "chemstyleId": 262,
        "playerRoleId": 18,
        "chemistry": 2,
        "isBestChemstyleAtChem": true
      },
      {
        "metaRating": 65.05979064730651,
        "chemstyleId": 262,
        "playerRoleId": 21,
        "chemistry": 2,
        "isBestChemstyleAtChem": true
      },
      {
        "metaRating": 65.049785773903,
        "chemstyleId": 262,
        "playerRoleId": 16,
        "chemistry": 2,
        "isBestChemstyleAtChem": true
      },
      {
        "metaRating": 65.0064909746856,
        "chemstyleId": 268,
        "playerRoleId": 19,
        "chemistry": 2,
        "isBestChemstyleAtChem": true
      },
      {
        "metaRating": 62.873885150247325,
        "chemstyleId": 267,
        "playerRoleId": 22,
        "chemistry": 2,
        "isBestChemstyleAtChem": true
      },
      {
        "metaRating": 62.2981491397117,
        "chemstyleId": 268,
        "playerRoleId": 15,
        "chemistry": 2,
        "isBestChemstyleAtChem": true
      },
      {
        "metaRating": 61.283080966300645,
        "chemstyleId": 268,
        "playerRoleId": 17,
        "chemistry": 2,
        "isBestChemstyleAtChem": true
      },
      {
        "metaRating": 69.34280830891744,
        "chemstyleId": 268,
        "playerRoleId": 14,
        "chemistry": 3,
        "isBestChemstyleAtChem": true
      },
      {
        "metaRating": 67.70784400072135,
        "chemstyleId": 268,
        "playerRoleId": 19,
        "chemistry": 3,
        "isBestChemstyleAtChem": true
      },
      {
        "metaRating": 67.1941097742313,
        "chemstyleId": 262,
        "playerRoleId": 20,
        "chemistry": 3,
        "isBestChemstyleAtChem": true
      },
      {
        "metaRating": 66.87058714991676,
        "chemstyleId": 268,
        "playerRoleId": 18,
        "chemistry": 3,
        "isBestChemstyleAtChem": true
      },
      {
        "metaRating": 66.84856357181,
        "chemstyleId": 262,
        "playerRoleId": 16,
        "chemistry": 3,
        "isBestChemstyleAtChem": true
      },
      {
        "metaRating": 66.61126091413989,
        "chemstyleId": 260,
        "playerRoleId": 21,
        "chemistry": 3,
        "isBestChemstyleAtChem": true
      },
      {
        "metaRating": 64.91122854232084,
        "chemstyleId": 268,
        "playerRoleId": 15,
        "chemistry": 3,
        "isBestChemstyleAtChem": true
      },
      {
        "metaRating": 64.76587684962524,
        "chemstyleId": 267,
        "playerRoleId": 22,
        "chemistry": 3,
        "isBestChemstyleAtChem": true
      },
      {
        "metaRating": 64.24332290613451,
        "chemstyleId": 268,
        "playerRoleId": 17,
        "chemistry": 3,
        "isBestChemstyleAtChem": true
      }
    ]
  }
]